[
    {
        "id": 87296,
        "externalOfficeCode": "SO28132BF6BCC93D6BA8799A6AFA8B3C",
        "name": "上海摩尔口腔医院",
        "address": "上海市普陀区梅川路1293号（真光路）",
        "contactPhone": "13162182127,13122782127",
        "picUrl": "https://pic5.40017.cn/i/ori/1wueo4Q1wAg.png",
        "intro": "",
        "workTime": "09：00-17：00",
        "distanceKm": null,
        "remark": "关爱口腔健康，绽放自信笑容",
        "customTag": "口碑商家",
        "qualityGrade": true,
        "demotionRank": 0,
        "invalidProjectConfig": "",
        "verifiedSales": 1229,
        "externalId": null,
        "highScoreRatio": 0.7273,
        "isAdv": false,
        "cityName": "上海",
        "cityId": 321,
        "productCode": "1000480",
        "productName": "优享窝沟-限上海"
    },
    {
        "id": 87304,
        "externalOfficeCode": "SOFD4E81B19AFC35A49A6998B618B539",
        "name": "上海摩尔同乐口腔医院",
        "address": "上海市闵行区七莘路1318号1幢强劲大厦7层（黎安路）",
        "contactPhone": "13162182127,13122782127",
        "picUrl": "https://pic5.40017.cn/i/ori/1wueo4Q1wAg.png",
        "intro": "",
        "workTime": "09：00-17：00",
        "distanceKm": null,
        "remark": "关爱口腔健康，绽放自信笑容",
        "customTag": "口碑商家",
        "qualityGrade": true,
        "demotionRank": 0,
        "invalidProjectConfig": "5",
        "verifiedSales": 1398,
        "externalId": null,
        "highScoreRatio": 1.0,
        "isAdv": false,
        "cityName": "上海",
        "cityId": 321,
        "productCode": "1000480",
        "productName": "优享窝沟-限上海"
    },
    {
        "id": 87298,
        "externalOfficeCode": "SO624F087A9BE635679830A6A1361CAF",
        "name": "上海摩尔星华口腔医院",
        "address": "上海市宝山区逸仙路1328号新业坊5号楼（殷高西路）",
        "contactPhone": "13162182127,13122782127",
        "picUrl": "https://pic5.40017.cn/i/ori/1wueo4Q1wAg.png",
        "intro": "",
        "workTime": "09：00-17：00",
        "distanceKm": null,
        "remark": "关爱口腔健康，绽放自信笑容",
        "customTag": "口碑商家 周末预约成功率高",
        "qualityGrade": true,
        "demotionRank": 0,
        "invalidProjectConfig": "",
        "verifiedSales": 1289,
        "externalId": null,
        "highScoreRatio": 1.0,
        "isAdv": false,
        "cityName": "上海",
        "cityId": 321,
        "productCode": "1000480",
        "productName": "优享窝沟-限上海"
    },
    {
        "id": 87307,
        "externalOfficeCode": "SOE07709ADC9B8380EAE4F35CE43183B",
        "name": "上海摩尔星嘉口腔医院",
        "address": "上海市嘉定区沪宜公路3078号",
        "contactPhone": "13162182127,13122782127",
        "picUrl": "https://pic5.40017.cn/i/ori/1wueo4Q1wAg.png",
        "intro": "",
        "workTime": "09：00-17：00",
        "distanceKm": null,
        "remark": "关爱口腔健康，绽放自信笑容",
        "customTag": "口碑商家 周末预约成功率高",
        "qualityGrade": true,
        "demotionRank": 0,
        "invalidProjectConfig": "",
        "verifiedSales": 956,
        "externalId": null,
        "highScoreRatio": 0.9375,
        "isAdv": false,
        "cityName": "上海",
        "cityId": 321,
        "productCode": "1000480",
        "productName": "优享窝沟-限上海"
    },
    {
        "id": 87301,
        "externalOfficeCode": "SOEB5DB74CEAF930089E16C95D5D14E0",
        "name": "上海摩尔星康口腔医院",
        "address": "上海市黄浦区新闸路158号1-2层",
        "contactPhone": "13162182127,13122782127",
        "picUrl": "https://pic5.40017.cn/i/ori/1wueo4Q1wAg.png",
        "intro": "",
        "workTime": "09：00-17：00",
        "distanceKm": null,
        "remark": "关爱口腔健康，绽放自信笑容",
        "customTag": "口碑商家 周末预约成功率高",
        "qualityGrade": true,
        "demotionRank": 0,
        "invalidProjectConfig": "",
        "verifiedSales": 403,
        "externalId": null,
        "highScoreRatio": 0.8,
        "isAdv": false,
        "cityName": "上海",
        "cityId": 321,
        "productCode": "1000480",
        "productName": "优享窝沟-限上海"
    },
    {
        "id": 87303,
        "externalOfficeCode": "SOEA9ACB62D58F3BB1B6E485D64B76FF",
        "name": "上海摩尔星恒口腔门诊部",
        "address": "上海市闵行区保乐路69弄56号1层（全家便利店旁）",
        "contactPhone": "13162182127,13122782127",
        "picUrl": "https://pic5.40017.cn/i/ori/1wueo4Q1wAg.png",
        "intro": "",
        "workTime": "09：00-17：00",
        "distanceKm": null,
        "remark": "关爱口腔健康，绽放自信笑容",
        "customTag": "口碑商家",
        "qualityGrade": true,
        "demotionRank": 0,
        "invalidProjectConfig": "",
        "verifiedSales": 144,
        "externalId": null,
        "highScoreRatio": 1.0,
        "isAdv": false,
        "cityName": "上海",
        "cityId": 321,
        "productCode": "1000480",
        "productName": "优享窝沟-限上海"
    },
    {
        "id": 87308,
        "externalOfficeCode": "SO01956B247C0834B4AB71DAF9E9F028",
        "name": "上海摩尔星悦口腔门诊部",
        "address": "上海市青浦区淀山湖大道218号吾悦广场3楼036,037",
        "contactPhone": "13162182127,13122782127",
        "picUrl": "https://pic5.40017.cn/i/ori/1wueo4Q1wAg.png",
        "intro": "",
        "workTime": "09：00-17：00",
        "distanceKm": null,
        "remark": "关爱口腔健康，绽放自信笑容",
        "customTag": "口碑商家",
        "qualityGrade": true,
        "demotionRank": 0,
        "invalidProjectConfig": "",
        "verifiedSales": 258,
        "externalId": null,
        "highScoreRatio": 1.0,
        "isAdv": false,
        "cityName": "上海",
        "cityId": 321,
        "productCode": "1000480",
        "productName": "优享窝沟-限上海"
    },
    {
        "id": 87312,
        "externalOfficeCode": "SO28FD5B00C3703B20AC70CA643DB174",
        "name": "上海摩尔星汇口腔医院",
        "address": "上海徐汇区漕宝路33号，日月光C座6L.",
        "contactPhone": "13162182127,13122782127",
        "picUrl": "https://pic5.40017.cn/i/ori/1wueo4Q1wAg.png",
        "intro": "",
        "workTime": "09：00-17：00",
        "distanceKm": null,
        "remark": "关爱口腔健康，绽放自信笑容",
        "customTag": "口碑商家",
        "qualityGrade": true,
        "demotionRank": 0,
        "invalidProjectConfig": "",
        "verifiedSales": 713,
        "externalId": null,
        "highScoreRatio": 1.0,
        "isAdv": false,
        "cityName": "上海",
        "cityId": 321,
        "productCode": "1000480",
        "productName": "优享窝沟-限上海"
    },
    {
        "id": 87309,
        "externalOfficeCode": "SO5E1F3023C83F3AE1B11D7337013D14",
        "name": "上海摩尔星浦口腔医院",
        "address": "上海市青浦区盈浦街道观云路372弄54号1-5层（万达茂对面）",
        "contactPhone": "13162182127,13122782127",
        "picUrl": "https://pic5.40017.cn/i/ori/1wueo4Q1wAg.png",
        "intro": "",
        "workTime": "09：00-17：00",
        "distanceKm": null,
        "remark": "关爱口腔健康，绽放自信笑容",
        "customTag": "口碑商家 周末预约成功率高",
        "qualityGrade": true,
        "demotionRank": 0,
        "invalidProjectConfig": "",
        "verifiedSales": 534,
        "externalId": null,
        "highScoreRatio": 1.0,
        "isAdv": false,
        "cityName": "上海",
        "cityId": 321,
        "productCode": "1000480",
        "productName": "优享窝沟-限上海"
    },
    {
        "id": 87311,
        "externalOfficeCode": "SOBA4F7073ABFC3BC1B6C7FABFB663E5",
        "name": "上海摩尔星象口腔医院",
        "address": "上海市静安区北京西路1271号2-4层",
        "contactPhone": "13162182127,13122782127",
        "picUrl": "https://pic5.40017.cn/i/ori/1wueo4Q1wAg.png",
        "intro": "",
        "workTime": "09：00-17：00",
        "distanceKm": null,
        "remark": "关爱口腔健康，绽放自信笑容",
        "customTag": "口碑商家 周末预约成功率高",
        "qualityGrade": true,
        "demotionRank": 0,
        "invalidProjectConfig": "",
        "verifiedSales": 374,
        "externalId": null,
        "highScoreRatio": 1.0,
        "isAdv": false,
        "cityName": "上海",
        "cityId": 321,
        "productCode": "1000480",
        "productName": "优享窝沟-限上海"
    },
    {
        "id": 87299,
        "externalOfficeCode": "SODD3923DC918E3FDF8741030A40C2DF",
        "name": "上海摩尔星贤口腔医院",
        "address": "上海市奉贤区环城东路793号4楼（航南公路，环城东路地铁站2号口处）",
        "contactPhone": "13162182127,13122782127",
        "picUrl": "https://pic5.40017.cn/i/ori/1wueo4Q1wAg.png",
        "intro": "",
        "workTime": "09：00-17：00",
        "distanceKm": null,
        "remark": "关爱口腔健康，绽放自信笑容",
        "customTag": "口碑商家",
        "qualityGrade": true,
        "demotionRank": 0,
        "invalidProjectConfig": "",
        "verifiedSales": 1507,
        "externalId": null,
        "highScoreRatio": 0.9091,
        "isAdv": false,
        "cityName": "上海",
        "cityId": 321,
        "productCode": "1000480",
        "productName": "优享窝沟-限上海"
    },
    {
        "id": 87295,
        "externalOfficeCode": "SOF9317DC12A2E31FE832E43BDB9142B",
        "name": "上海摩尔星辰口腔医院",
        "address": "上海市浦东新区浦建路15号新塘桥生活广场（塘桥地铁站4号口处）",
        "contactPhone": "13162182127,13122782127",
        "picUrl": "https://pic5.40017.cn/i/ori/1wueo4Q1wAg.png",
        "intro": "",
        "workTime": "09：00-17：00",
        "distanceKm": null,
        "remark": "关爱口腔健康，绽放自信笑容",
        "customTag": "口碑商家 周末预约成功率高",
        "qualityGrade": true,
        "demotionRank": 0,
        "invalidProjectConfig": "3",
        "verifiedSales": 1136,
        "externalId": null,
        "highScoreRatio": 1.0,
        "isAdv": false,
        "cityName": "上海",
        "cityId": 321,
        "productCode": "1000480",
        "productName": "优享窝沟-限上海"
    },
    {
        "id": 87302,
        "externalOfficeCode": "SOD4D1BB50437B3B90901D910298313A",
        "name": "上海摩尔申洁口腔医院",
        "address": "上海市静安区江场西路300号1幢",
        "contactPhone": "13162182127,13122782127",
        "picUrl": "https://pic5.40017.cn/i/ori/1wueo4Q1wAg.png",
        "intro": "",
        "workTime": "09：00-17：00",
        "distanceKm": null,
        "remark": "关爱口腔健康，绽放自信笑容",
        "customTag": "口碑商家",
        "qualityGrade": true,
        "demotionRank": 0,
        "invalidProjectConfig": "",
        "verifiedSales": 470,
        "externalId": null,
        "highScoreRatio": 1.0,
        "isAdv": false,
        "cityName": "上海",
        "cityId": 321,
        "productCode": "1000480",
        "productName": "优享窝沟-限上海"
    },
    {
        "id": 94036,
        "externalOfficeCode": "SO78AF940C9BC33030B65E12B43F3812",
        "name": "上海华齿口腔门诊部",
        "address": "浦东新区金台路104号（距枣庄路200米），陆行中学南校旁",
        "contactPhone": "02150706472",
        "picUrl": "https://pic5.40017.cn/i/ori/1GYFiJWBTGw.jpg",
        "intro": "",
        "workTime": "9：00-12：00，14：00-18：00",
        "distanceKm": null,
        "remark": "",
        "customTag": "",
        "qualityGrade": false,
        "demotionRank": 0,
        "invalidProjectConfig": "8,4,5",
        "verifiedSales": 63,
        "externalId": null,
        "highScoreRatio": 0.0,
        "isAdv": false,
        "cityName": "上海",
        "cityId": 321,
        "productCode": "1000480",
        "productName": "优享窝沟-限上海"
    },
    {
        "id": 87369,
        "externalOfficeCode": "SO33FA29FBC8543428AC50B1E8F83392",
        "name": "上海奥华口腔门诊部",
        "address": "上海市浦东新区东方路710号1楼105室",
        "contactPhone": "02123301211",
        "picUrl": "https://pic5.40017.cn/i/ori/1wumsh1qQW4.png",
        "intro": "",
        "workTime": "9:30-17:00",
        "distanceKm": null,
        "remark": "关爱口腔健康，绽放自信笑容",
        "customTag": "",
        "qualityGrade": false,
        "demotionRank": 0,
        "invalidProjectConfig": "",
        "verifiedSales": 125,
        "externalId": null,
        "highScoreRatio": 0.0,
        "isAdv": false,
        "cityName": "上海",
        "cityId": 321,
        "productCode": "1000480",
        "productName": "优享窝沟-限上海"
    },
    {
        "id": 87385,
        "externalOfficeCode": "SO14DDF0DE99CB374082D98AA4B16E33",
        "name": "上海泰康拜博丽德口腔门诊部",
        "address": "上海市长宁区淞虹路377号L2层T2-N02室",
        "contactPhone": "02123301211",
        "picUrl": "https://pic5.40017.cn/i/ori/1wumsh1qQW4.png",
        "intro": "",
        "workTime": "9:30-17:00",
        "distanceKm": null,
        "remark": "关爱口腔健康，绽放自信笑容",
        "customTag": "",
        "qualityGrade": false,
        "demotionRank": 0,
        "invalidProjectConfig": "",
        "verifiedSales": 163,
        "externalId": null,
        "highScoreRatio": 0.75,
        "isAdv": false,
        "cityName": "上海",
        "cityId": 321,
        "productCode": "1000480",
        "productName": "优享窝沟-限上海"
    },
    {
        "id": 87391,
        "externalOfficeCode": "SOCEC0BF058C593C77B0E249DF1F3E9B",
        "name": "上海泰康拜博仁尔口腔门诊部",
        "address": "上海市浦东新区耀体路212号晶耀前滩L113A",
        "contactPhone": "02123301211",
        "picUrl": "https://pic5.40017.cn/i/ori/1wumsh1qQW4.png",
        "intro": "",
        "workTime": "9:30-17:00",
        "distanceKm": null,
        "remark": "关爱口腔健康，绽放自信笑容",
        "customTag": "",
        "qualityGrade": false,
        "demotionRank": 0,
        "invalidProjectConfig": "",
        "verifiedSales": 221,
        "externalId": null,
        "highScoreRatio": 1.0,
        "isAdv": false,
        "cityName": "上海",
        "cityId": 321,
        "productCode": "1000480",
        "productName": "优享窝沟-限上海"
    },
    {
        "id": 87368,
        "externalOfficeCode": "SOBFF4AA9AAD983C8BB09FC0F171AD46",
        "name": "上海泰康拜博六和口腔门诊部",
        "address": "上海市杨浦区大连路1192号",
        "contactPhone": "02123301211",
        "picUrl": "https://pic5.40017.cn/i/ori/1wumsh1qQW4.png",
        "intro": "",
        "workTime": "9:30-17:00",
        "distanceKm": null,
        "remark": "关爱口腔健康，绽放自信笑容",
        "customTag": "",
        "qualityGrade": false,
        "demotionRank": 0,
        "invalidProjectConfig": "",
        "verifiedSales": 127,
        "externalId": null,
        "highScoreRatio": 0.0,
        "isAdv": false,
        "cityName": "上海",
        "cityId": 321,
        "productCode": "1000480",
        "productName": "优享窝沟-限上海"
    },
    {
        "id": 87392,
        "externalOfficeCode": "SOF9050D3EBDAD36F8B493C706EA97CE",
        "name": "上海泰康拜博凯尔口腔诊所",
        "address": "长宁区凯旋路1398号8号楼401-501室",
        "contactPhone": "02123301211",
        "picUrl": "https://pic5.40017.cn/i/ori/1wumsh1qQW4.png",
        "intro": "",
        "workTime": "9:30-17:00",
        "distanceKm": null,
        "remark": "关爱口腔健康，绽放自信笑容",
        "customTag": "",
        "qualityGrade": false,
        "demotionRank": 0,
        "invalidProjectConfig": "",
        "verifiedSales": 102,
        "externalId": null,
        "highScoreRatio": 1.0,
        "isAdv": false,
        "cityName": "上海",
        "cityId": 321,
        "productCode": "1000480",
        "productName": "优享窝沟-限上海"
    },
    {
        "id": 87375,
        "externalOfficeCode": "SO876D977C3A5838819408965CD5AFA3",
        "name": "上海泰康拜博南尔口腔门诊部",
        "address": "上海市奉贤区南桥路366号",
        "contactPhone": "02123301211",
        "picUrl": "https://pic5.40017.cn/i/ori/1wumsh1qQW4.png",
        "intro": "",
        "workTime": "9:30-17:00",
        "distanceKm": null,
        "remark": "关爱口腔健康，绽放自信笑容",
        "customTag": "",
        "qualityGrade": false,
        "demotionRank": 0,
        "invalidProjectConfig": "",
        "verifiedSales": 181,
        "externalId": null,
        "highScoreRatio": 1.0,
        "isAdv": false,
        "cityName": "上海",
        "cityId": 321,
        "productCode": "1000480",
        "productName": "优享窝沟-限上海"
    },
    {
        "id": 87365,
        "externalOfficeCode": "SOECEFD5F611793E3688E5118E8FA362",
        "name": "上海泰康拜博博尔口腔门诊部",
        "address": "上海市黄浦区徐家汇路338号3楼",
        "contactPhone": "02123301211",
        "picUrl": "https://pic5.40017.cn/i/ori/1wumsh1qQW4.png",
        "intro": "",
        "workTime": "9:30-17:00",
        "distanceKm": null,
        "remark": "关爱口腔健康，绽放自信笑容",
        "customTag": "",
        "qualityGrade": false,
        "demotionRank": 0,
        "invalidProjectConfig": "",
        "verifiedSales": 100,
        "externalId": null,
        "highScoreRatio": 0.0,
        "isAdv": false,
        "cityName": "上海",
        "cityId": 321,
        "productCode": "1000480",
        "productName": "优享窝沟-限上海"
    },
    {
        "id": 87367,
        "externalOfficeCode": "SO2B6A71FAF6EF3183947EB4BC4EF0F6",
        "name": "上海泰康拜博吉尔口腔门诊部",
        "address": "上海市闵行区虹井路288号乐虹坊3楼",
        "contactPhone": "02123301211",
        "picUrl": "https://pic5.40017.cn/i/ori/1wumsh1qQW4.png",
        "intro": "",
        "workTime": "9:30-17:00",
        "distanceKm": null,
        "remark": "关爱口腔健康，绽放自信笑容",
        "customTag": "",
        "qualityGrade": false,
        "demotionRank": 0,
        "invalidProjectConfig": "",
        "verifiedSales": 132,
        "externalId": null,
        "highScoreRatio": 1.0,
        "isAdv": false,
        "cityName": "上海",
        "cityId": 321,
        "productCode": "1000480",
        "productName": "优享窝沟-限上海"
    },
    {
        "id": 87372,
        "externalOfficeCode": "SO66A74CC2F8553E5DA7B1D26CA09FFB",
        "name": "上海泰康拜博喆尔口腔门诊部",
        "address": "上海市浦东新区梅花路1099号211、222室",
        "contactPhone": "02123301211",
        "picUrl": "https://pic5.40017.cn/i/ori/1wumsh1qQW4.png",
        "intro": "",
        "workTime": "9:30-17:00",
        "distanceKm": null,
        "remark": "关爱口腔健康，绽放自信笑容",
        "customTag": "",
        "qualityGrade": false,
        "demotionRank": 0,
        "invalidProjectConfig": "",
        "verifiedSales": 208,
        "externalId": null,
        "highScoreRatio": 1.0,
        "isAdv": false,
        "cityName": "上海",
        "cityId": 321,
        "productCode": "1000480",
        "productName": "优享窝沟-限上海"
    },
    {
        "id": 87373,
        "externalOfficeCode": "SOD57F811FFFA739FFB0DBBFC2332A7E",
        "name": "上海泰康拜博宝尔口腔门诊部",
        "address": "上海市宝山区牡丹江路1272号6楼",
        "contactPhone": "02123301211",
        "picUrl": "https://pic5.40017.cn/i/ori/1wumsh1qQW4.png",
        "intro": "",
        "workTime": "9:30-17:00",
        "distanceKm": null,
        "remark": "关爱口腔健康，绽放自信笑容",
        "customTag": "",
        "qualityGrade": false,
        "demotionRank": 0,
        "invalidProjectConfig": "",
        "verifiedSales": 91,
        "externalId": null,
        "highScoreRatio": 1.0,
        "isAdv": false,
        "cityName": "上海",
        "cityId": 321,
        "productCode": "1000480",
        "productName": "优享窝沟-限上海"
    },
    {
        "id": 87388,
        "externalOfficeCode": "SOB519ECA9BF323F8F93708193844220",
        "name": "上海泰康拜博广尔口腔门诊部",
        "address": "闵行区漕宝路3366号L4层L424B",
        "contactPhone": "02123301211",
        "picUrl": "https://pic5.40017.cn/i/ori/1wumsh1qQW4.png",
        "intro": "",
        "workTime": "9:30-17:00",
        "distanceKm": null,
        "remark": "关爱口腔健康，绽放自信笑容",
        "customTag": "",
        "qualityGrade": false,
        "demotionRank": 0,
        "invalidProjectConfig": "",
        "verifiedSales": 138,
        "externalId": null,
        "highScoreRatio": 0.6667,
        "isAdv": false,
        "cityName": "上海",
        "cityId": 321,
        "productCode": "1000480",
        "productName": "优享窝沟-限上海"
    },
    {
        "id": 87379,
        "externalOfficeCode": "SOA5C798F262D93431AE0C6C5C25A130",
        "name": "上海泰康拜博康乾口腔门诊部",
        "address": "上海市宝山区殷高西路510号2楼",
        "contactPhone": "02123301211",
        "picUrl": "https://pic5.40017.cn/i/ori/1wumsh1qQW4.png",
        "intro": "",
        "workTime": "9:30-17:00",
        "distanceKm": null,
        "remark": "关爱口腔健康，绽放自信笑容",
        "customTag": "",
        "qualityGrade": false,
        "demotionRank": 0,
        "invalidProjectConfig": "",
        "verifiedSales": 136,
        "externalId": null,
        "highScoreRatio": 0.0,
        "isAdv": false,
        "cityName": "上海",
        "cityId": 321,
        "productCode": "1000480",
        "productName": "优享窝沟-限上海"
    },
    {
        "id": 87376,
        "externalOfficeCode": "SO96322AAC8A763CF6B16BC906C1FE80",
        "name": "上海泰康拜博康尔口腔门诊部",
        "address": "上海市宝山区共和新路5000弄3号楼201室",
        "contactPhone": "02123301211",
        "picUrl": "https://pic5.40017.cn/i/ori/1wumsh1qQW4.png",
        "intro": "",
        "workTime": "9:30-17:00",
        "distanceKm": null,
        "remark": "关爱口腔健康，绽放自信笑容",
        "customTag": "",
        "qualityGrade": false,
        "demotionRank": 0,
        "invalidProjectConfig": "",
        "verifiedSales": 214,
        "externalId": null,
        "highScoreRatio": 1.0,
        "isAdv": false,
        "cityName": "上海",
        "cityId": 321,
        "productCode": "1000480",
        "productName": "优享窝沟-限上海"
    },
    {
        "id": 87606,
        "externalOfficeCode": "SO8448DA94C0053F64B249C785CA2327",
        "name": "上海泰康拜博昌森口腔门诊部",
        "address": "静安区万航渡路889号889广场3层L3-09室",
        "contactPhone": "02123301211",
        "picUrl": "https://pic5.40017.cn/i/ori/1wumsh1qQW4.png",
        "intro": "",
        "workTime": "9:30-17:00",
        "distanceKm": null,
        "remark": "关爱口腔健康，绽放自信笑容",
        "customTag": "",
        "qualityGrade": false,
        "demotionRank": 0,
        "invalidProjectConfig": "",
        "verifiedSales": 96,
        "externalId": null,
        "highScoreRatio": 0.0,
        "isAdv": false,
        "cityName": "上海",
        "cityId": 321,
        "productCode": "1000480",
        "productName": "优享窝沟-限上海"
    },
    {
        "id": 87384,
        "externalOfficeCode": "SOFC7976A951383A518D6FEBD8736CD6",
        "name": "上海泰康拜博星尔口腔门诊部",
        "address": "上海市普陀区中山北路3300号4157室（环球港4楼）",
        "contactPhone": "02123301211",
        "picUrl": "https://pic5.40017.cn/i/ori/1wumsh1qQW4.png",
        "intro": "",
        "workTime": "9:30-17:00",
        "distanceKm": null,
        "remark": "关爱口腔健康，绽放自信笑容",
        "customTag": "",
        "qualityGrade": false,
        "demotionRank": 0,
        "invalidProjectConfig": "",
        "verifiedSales": 146,
        "externalId": null,
        "highScoreRatio": 1.0,
        "isAdv": false,
        "cityName": "上海",
        "cityId": 321,
        "productCode": "1000480",
        "productName": "优享窝沟-限上海"
    },
    {
        "id": 87377,
        "externalOfficeCode": "SO3081BEAFAD653E4EA833DE1D5A6BF4",
        "name": "上海泰康拜博浦尔口腔门诊部",
        "address": "上海市徐汇区浦北路9号家乐福4楼",
        "contactPhone": "02123301211",
        "picUrl": "https://pic5.40017.cn/i/ori/1wumsh1qQW4.png",
        "intro": "",
        "workTime": "9:30-17:00",
        "distanceKm": null,
        "remark": "关爱口腔健康，绽放自信笑容",
        "customTag": "",
        "qualityGrade": false,
        "demotionRank": 0,
        "invalidProjectConfig": "",
        "verifiedSales": 221,
        "externalId": null,
        "highScoreRatio": 0.0,
        "isAdv": false,
        "cityName": "上海",
        "cityId": 321,
        "productCode": "1000480",
        "productName": "优享窝沟-限上海"
    },
    {
        "id": 87378,
        "externalOfficeCode": "SO2F6BDBD9438A39F0A4E6AAFF01775A",
        "name": "上海泰康拜博瑞吉尔口腔门诊部",
        "address": "上海市徐汇区徐汇区云锦路701号T1楼3层304,305号单元（西岸凤巢）",
        "contactPhone": "02123301211",
        "picUrl": "https://pic5.40017.cn/i/ori/1wumsh1qQW4.png",
        "intro": "",
        "workTime": "9:30-17:00",
        "distanceKm": null,
        "remark": "关爱口腔健康，绽放自信笑容",
        "customTag": "",
        "qualityGrade": false,
        "demotionRank": 0,
        "invalidProjectConfig": "",
        "verifiedSales": 181,
        "externalId": null,
        "highScoreRatio": 1.0,
        "isAdv": false,
        "cityName": "上海",
        "cityId": 321,
        "productCode": "1000480",
        "productName": "优享窝沟-限上海"
    },
    {
        "id": 87386,
        "externalOfficeCode": "SO7BBF6D743D163E36A7AC0387FD61B4",
        "name": "上海泰康拜博荣尔口腔门诊部",
        "address": "寿阳路99弄协信星光广场17.18.19号L2层S202号",
        "contactPhone": "02123301211",
        "picUrl": "https://pic5.40017.cn/i/ori/1wumsh1qQW4.png",
        "intro": "",
        "workTime": "9:30-17:00",
        "distanceKm": null,
        "remark": "关爱口腔健康，绽放自信笑容",
        "customTag": "",
        "qualityGrade": false,
        "demotionRank": 0,
        "invalidProjectConfig": "",
        "verifiedSales": 156,
        "externalId": null,
        "highScoreRatio": 1.0,
        "isAdv": false,
        "cityName": "上海",
        "cityId": 321,
        "productCode": "1000480",
        "productName": "优享窝沟-限上海"
    },
    {
        "id": 87381,
        "externalOfficeCode": "SO015F5A90785D3D2B9D860AC9464FA6",
        "name": "上海泰康拜博虹尔口腔门诊部",
        "address": "上海市虹口区天宝路280弄17号B1-20",
        "contactPhone": "02123301211",
        "picUrl": "https://pic5.40017.cn/i/ori/1wumsh1qQW4.png",
        "intro": "",
        "workTime": "9:30-17:00",
        "distanceKm": null,
        "remark": "关爱口腔健康，绽放自信笑容",
        "customTag": "",
        "qualityGrade": false,
        "demotionRank": 0,
        "invalidProjectConfig": "",
        "verifiedSales": 126,
        "externalId": null,
        "highScoreRatio": 1.0,
        "isAdv": false,
        "cityName": "上海",
        "cityId": 321,
        "productCode": "1000480",
        "productName": "优享窝沟-限上海"
    },
    {
        "id": 87380,
        "externalOfficeCode": "SO90C7A517CF8434C29FECFAFF13F5DE",
        "name": "上海泰康拜博静尔口腔门诊部",
        "address": "上海市静安区愚园路68号晶品大厦5-13",
        "contactPhone": "02123301211",
        "picUrl": "https://pic5.40017.cn/i/ori/1wumsh1qQW4.png",
        "intro": "",
        "workTime": "9:30-17:00",
        "distanceKm": null,
        "remark": "关爱口腔健康，绽放自信笑容",
        "customTag": "",
        "qualityGrade": false,
        "demotionRank": 0,
        "invalidProjectConfig": "",
        "verifiedSales": 107,
        "externalId": null,
        "highScoreRatio": 1.0,
        "isAdv": false,
        "cityName": "上海",
        "cityId": 321,
        "productCode": "1000480",
        "productName": "优享窝沟-限上海"
    },
    {
        "id": 87371,
        "externalOfficeCode": "SOC338CDF004653315AD27C54B13BB5E",
        "name": "上海泰康拜博龙尔口腔门诊部",
        "address": "上海市虹口区西江湾路388号凯德龙之梦购物中心B座四楼04-12",
        "contactPhone": "02123301211",
        "picUrl": "https://pic5.40017.cn/i/ori/1wumsh1qQW4.png",
        "intro": "",
        "workTime": "9:30-17:00",
        "distanceKm": null,
        "remark": "关爱口腔健康，绽放自信笑容",
        "customTag": "",
        "qualityGrade": false,
        "demotionRank": 0,
        "invalidProjectConfig": "",
        "verifiedSales": 115,
        "externalId": null,
        "highScoreRatio": 1.0,
        "isAdv": false,
        "cityName": "上海",
        "cityId": 321,
        "productCode": "1000480",
        "productName": "优享窝沟-限上海"
    },
    {
        "id": 87364,
        "externalOfficeCode": "SO9AE593950D0230D89D7933E270883D",
        "name": "上海泰康拜尔口腔门诊部",
        "address": "上海市长宁区长宁路1018号5楼",
        "contactPhone": "02123301211",
        "picUrl": "https://pic5.40017.cn/i/ori/1wumsh1qQW4.png",
        "intro": "",
        "workTime": "9:30-17:00",
        "distanceKm": null,
        "remark": "关爱口腔健康，绽放自信笑容",
        "customTag": "",
        "qualityGrade": false,
        "demotionRank": 0,
        "invalidProjectConfig": "",
        "verifiedSales": 114,
        "externalId": null,
        "highScoreRatio": 1.0,
        "isAdv": false,
        "cityName": "上海",
        "cityId": 321,
        "productCode": "1000480",
        "productName": "优享窝沟-限上海"
    },
    {
        "id": 94381,
        "externalOfficeCode": "SO69086B25802D1021U1",
        "name": "上海隽雅口腔门诊部",
        "address": "上海市嘉定区绿苑路510、512号1层101室、103室、2层201室",
        "contactPhone": "4007788190",
        "picUrl": "https://pic5.40017.cn/i/ori/1I04dzZgsKY.png",
        "intro": "",
        "workTime": "9：00-17：00",
        "distanceKm": null,
        "remark": "",
        "customTag": "",
        "qualityGrade": false,
        "demotionRank": 0,
        "invalidProjectConfig": "",
        "verifiedSales": 7,
        "externalId": null,
        "highScoreRatio": 0.0,
        "isAdv": false,
        "cityName": "上海",
        "cityId": 321,
        "productCode": "1000480",
        "productName": "优享窝沟-限上海"
    },
    {
        "id": 94038,
        "externalOfficeCode": "SO574160CD900F3F6DBC915790D5A2D2",
        "name": "健齿口腔门诊部",
        "address": "浦东新区昌里东路111号",
        "contactPhone": "02150862184",
        "picUrl": "https://pic5.40017.cn/i/ori/1GYFiJWBTGw.jpg",
        "intro": "",
        "workTime": "9：00-12：00，14：00-18：00",
        "distanceKm": null,
        "remark": "",
        "customTag": "",
        "qualityGrade": false,
        "demotionRank": 0,
        "invalidProjectConfig": "8,4,5",
        "verifiedSales": 25,
        "externalId": null,
        "highScoreRatio": 0.0,
        "isAdv": false,
        "cityName": "上海",
        "cityId": 321,
        "productCode": "1000480",
        "productName": "优享窝沟-限上海"
    },
    {
        "id": 93241,
        "externalOfficeCode": "SO689UD646711BC9U188",
        "name": "华尔康口腔（泗泾皓运店）",
        "address": "上海市松江区泗泾镇泗凤公路102-116号",
        "contactPhone": "19352123459",
        "picUrl": "https://pic5.40017.cn/i/ori/1FR8Xzp6GiY.png",
        "intro": "",
        "workTime": "9：00-17：00",
        "distanceKm": null,
        "remark": "",
        "customTag": "",
        "qualityGrade": false,
        "demotionRank": 0,
        "invalidProjectConfig": "",
        "verifiedSales": 148,
        "externalId": null,
        "highScoreRatio": 0.0,
        "isAdv": false,
        "cityName": "上海",
        "cityId": 321,
        "productCode": "1000480",
        "productName": "优享窝沟-限上海"
    },
    {
        "id": 93240,
        "externalOfficeCode": "SO689UD5CD711BC9D1U4",
        "name": "华尔康星杰口腔医院",
        "address": "上海市普陀区中山北路2143号1幢",
        "contactPhone": "19352123459",
        "picUrl": "https://pic5.40017.cn/i/ori/1FR8Xzp6GiY.png",
        "intro": "",
        "workTime": "9：00-17：00",
        "distanceKm": null,
        "remark": "",
        "customTag": "",
        "qualityGrade": false,
        "demotionRank": 0,
        "invalidProjectConfig": "",
        "verifiedSales": 29,
        "externalId": null,
        "highScoreRatio": 1.0,
        "isAdv": false,
        "cityName": "上海",
        "cityId": 321,
        "productCode": "1000480",
        "productName": "优享窝沟-限上海"
    },
    {
        "id": 94037,
        "externalOfficeCode": "SO6CF9796BB63F32E889DFFF084C8E80",
        "name": "华盛口腔门诊部",
        "address": "浦东新区上南路3019号",
        "contactPhone": "02138681282",
        "picUrl": "https://pic5.40017.cn/i/ori/1GYFiJWBTGw.jpg",
        "intro": "",
        "workTime": "9：00-12：00，14：00-18：00",
        "distanceKm": null,
        "remark": "",
        "customTag": "",
        "qualityGrade": false,
        "demotionRank": 0,
        "invalidProjectConfig": "8,4,5",
        "verifiedSales": 43,
        "externalId": null,
        "highScoreRatio": 0.0,
        "isAdv": false,
        "cityName": "上海",
        "cityId": 321,
        "productCode": "1000480",
        "productName": "优享窝沟-限上海"
    },
    {
        "id": 94031,
        "externalOfficeCode": "SOA0AE74F828C73330889AFEA212FE91",
        "name": "华茂口腔门诊部",
        "address": "杨浦区长海一村53号",
        "contactPhone": "02165573073",
        "picUrl": "https://pic5.40017.cn/i/ori/1GYFiJWBTGw.jpg",
        "intro": "",
        "workTime": "9：00-12：00，14：00-18：00",
        "distanceKm": null,
        "remark": "",
        "customTag": "",
        "qualityGrade": false,
        "demotionRank": 0,
        "invalidProjectConfig": "8,4,5",
        "verifiedSales": 6,
        "externalId": null,
        "highScoreRatio": 0.0,
        "isAdv": false,
        "cityName": "上海",
        "cityId": 321,
        "productCode": "1000480",
        "productName": "优享窝沟-限上海"
    },
    {
        "id": 94043,
        "externalOfficeCode": "SO39E2A97C0D4031599460B613AD8B8A",
        "name": "华齿佳齿口腔门诊部",
        "address": "闵行区石屏路419号",
        "contactPhone": "02154711146",
        "picUrl": "https://pic5.40017.cn/i/ori/1GYFiJWBTGw.jpg",
        "intro": "",
        "workTime": "9：00-12：00，14：00-18：00",
        "distanceKm": null,
        "remark": "",
        "customTag": "",
        "qualityGrade": false,
        "demotionRank": 0,
        "invalidProjectConfig": "8,4,5",
        "verifiedSales": 29,
        "externalId": null,
        "highScoreRatio": 0.0,
        "isAdv": false,
        "cityName": "上海",
        "cityId": 321,
        "productCode": "1000480",
        "productName": "优享窝沟-限上海"
    },
    {
        "id": 94030,
        "externalOfficeCode": "SO77073A03924437298FA7C46C81A2C3",
        "name": "华齿华开口腔门诊部",
        "address": "杨浦区开鲁路329号",
        "contactPhone": "02165322832",
        "picUrl": "https://pic5.40017.cn/i/ori/1GYFiJWBTGw.jpg",
        "intro": "",
        "workTime": "9：00-12：00，14：00-18：00",
        "distanceKm": null,
        "remark": "",
        "customTag": "",
        "qualityGrade": false,
        "demotionRank": 0,
        "invalidProjectConfig": "8,4,5",
        "verifiedSales": 22,
        "externalId": null,
        "highScoreRatio": 0.0,
        "isAdv": false,
        "cityName": "上海",
        "cityId": 321,
        "productCode": "1000480",
        "productName": "优享窝沟-限上海"
    },
    {
        "id": 94028,
        "externalOfficeCode": "SO4FC41AD4D1A133138B2087EC4BCC8D",
        "name": "华齿华驰口腔门诊部",
        "address": "黄浦区复兴东路1117号",
        "contactPhone": "02133300391",
        "picUrl": "https://pic5.40017.cn/i/ori/1GYFiJWBTGw.jpg",
        "intro": "",
        "workTime": "9：00-12：00，14：00-18：00",
        "distanceKm": null,
        "remark": "",
        "customTag": "",
        "qualityGrade": false,
        "demotionRank": 0,
        "invalidProjectConfig": "8",
        "verifiedSales": 8,
        "externalId": null,
        "highScoreRatio": 1.0,
        "isAdv": false,
        "cityName": "上海",
        "cityId": 321,
        "productCode": "1000480",
        "productName": "优享窝沟-限上海"
    },
    {
        "id": 94047,
        "externalOfficeCode": "SO92D41A95E6753545989C69EBD2E171",
        "name": "华齿古思口腔门诊部",
        "address": "金山区枫泾镇思古弄118-122号",
        "contactPhone": "02167228669",
        "picUrl": "https://pic5.40017.cn/i/ori/1GYFiJWBTGw.jpg",
        "intro": "",
        "workTime": "9：00-12：00，14：00-18：00",
        "distanceKm": null,
        "remark": "",
        "customTag": "",
        "qualityGrade": false,
        "demotionRank": 0,
        "invalidProjectConfig": "8,4,5",
        "verifiedSales": 5,
        "externalId": null,
        "highScoreRatio": 0.0,
        "isAdv": false,
        "cityName": "上海",
        "cityId": 321,
        "productCode": "1000480",
        "productName": "优享窝沟-限上海"
    },
    {
        "id": 94045,
        "externalOfficeCode": "SOA61F92230EDA3740ADB392A57678EF",
        "name": "华齿嘉亭口腔门诊部",
        "address": "嘉定区安亭镇新源路196号（泽普路路口）",
        "contactPhone": "02139949281",
        "picUrl": "https://pic5.40017.cn/i/ori/1GYFiJWBTGw.jpg",
        "intro": "",
        "workTime": "9：00-12：00，14：00-18：00",
        "distanceKm": null,
        "remark": "",
        "customTag": "",
        "qualityGrade": false,
        "demotionRank": 0,
        "invalidProjectConfig": "8,4,5",
        "verifiedSales": 43,
        "externalId": null,
        "highScoreRatio": 0.0,
        "isAdv": false,
        "cityName": "上海",
        "cityId": 321,
        "productCode": "1000480",
        "productName": "优享窝沟-限上海"
    },
    {
        "id": 94032,
        "externalOfficeCode": "SOE46415EAEFCB3BC48083F943E7831A",
        "name": "华齿国定口腔门诊部",
        "address": "杨浦区国定路335号（颐高数码广场3楼）邯郸路路口",
        "contactPhone": "02155661632",
        "picUrl": "https://pic5.40017.cn/i/ori/1GYFiJWBTGw.jpg",
        "intro": "",
        "workTime": "9：00-12：00，14：00-18：00",
        "distanceKm": null,
        "remark": "",
        "customTag": "",
        "qualityGrade": false,
        "demotionRank": 0,
        "invalidProjectConfig": "8,4,5",
        "verifiedSales": 22,
        "externalId": null,
        "highScoreRatio": 0.0,
        "isAdv": false,
        "cityName": "上海",
        "cityId": 321,
        "productCode": "1000480",
        "productName": "优享窝沟-限上海"
    },
    {
        "id": 94048,
        "externalOfficeCode": "SO5E69E6AC138C30C3B996104E32BC5B",
        "name": "华齿奉南口腔门诊部",
        "address": "奉贤区南桥镇百齐路288号（南桥百联购物中心二期四楼，电影院对面）",
        "contactPhone": "02167188951",
        "picUrl": "https://pic5.40017.cn/i/ori/1GYFiJWBTGw.jpg",
        "intro": "",
        "workTime": "9：00-12：00，14：00-18：00",
        "distanceKm": null,
        "remark": "",
        "customTag": "",
        "qualityGrade": false,
        "demotionRank": 0,
        "invalidProjectConfig": "8,4,5",
        "verifiedSales": 14,
        "externalId": null,
        "highScoreRatio": 0.0,
        "isAdv": false,
        "cityName": "上海",
        "cityId": 321,
        "productCode": "1000480",
        "productName": "优享窝沟-限上海"
    },
    {
        "id": 94044,
        "externalOfficeCode": "SOB5356866E4F2310DBDFBE7764116CB",
        "name": "华齿尚仁口腔门诊部",
        "address": "松江区环城路260号（近中山东路）",
        "contactPhone": "02167831199",
        "picUrl": "https://pic5.40017.cn/i/ori/1GYFiJWBTGw.jpg",
        "intro": "",
        "workTime": "9：00-12：00，14：00-18：00",
        "distanceKm": null,
        "remark": "",
        "customTag": "",
        "qualityGrade": false,
        "demotionRank": 0,
        "invalidProjectConfig": "8,4,5",
        "verifiedSales": 29,
        "externalId": null,
        "highScoreRatio": 0.0,
        "isAdv": false,
        "cityName": "上海",
        "cityId": 321,
        "productCode": "1000480",
        "productName": "优享窝沟-限上海"
    },
    {
        "id": 94029,
        "externalOfficeCode": "SO4A825968AB933D39BCC0511824DC6B",
        "name": "华齿尚信口腔门诊部",
        "address": "黄浦区九江路399号（华盛大厦3楼）",
        "contactPhone": "02163088208",
        "picUrl": "https://pic5.40017.cn/i/ori/1GYFiJWBTGw.jpg",
        "intro": "",
        "workTime": "9：00-12：00，14：00-18：00",
        "distanceKm": null,
        "remark": "",
        "customTag": "",
        "qualityGrade": false,
        "demotionRank": 0,
        "invalidProjectConfig": "8,4,5",
        "verifiedSales": 6,
        "externalId": null,
        "highScoreRatio": 0.0,
        "isAdv": false,
        "cityName": "上海",
        "cityId": 321,
        "productCode": "1000480",
        "productName": "优享窝沟-限上海"
    },
    {
        "id": 94040,
        "externalOfficeCode": "SO411AE4AB5D273AF1B742EF69ED880A",
        "name": "华齿尚浦口腔门诊部",
        "address": "浦东新区浦东南路999号（新梅联合广场3楼）",
        "contactPhone": "02150896160",
        "picUrl": "https://pic5.40017.cn/i/ori/1GYFiJWBTGw.jpg",
        "intro": "",
        "workTime": "9：00-12：00，14：00-18：00",
        "distanceKm": null,
        "remark": "",
        "customTag": "",
        "qualityGrade": false,
        "demotionRank": 0,
        "invalidProjectConfig": "8,4,5",
        "verifiedSales": 40,
        "externalId": null,
        "highScoreRatio": 1.0,
        "isAdv": false,
        "cityName": "上海",
        "cityId": 321,
        "productCode": "1000480",
        "productName": "优享窝沟-限上海"
    },
    {
        "id": 94041,
        "externalOfficeCode": "SOEBF5CBBD76C43A26AEEFC47AEB512E",
        "name": "华齿尚荟口腔医院",
        "address": "徐汇区肇嘉浜路989号1层",
        "contactPhone": "02133686658",
        "picUrl": "https://pic5.40017.cn/i/ori/1GYFiJWBTGw.jpg",
        "intro": "",
        "workTime": "9：00-12：00，14：00-18：00",
        "distanceKm": null,
        "remark": "",
        "customTag": "",
        "qualityGrade": false,
        "demotionRank": 0,
        "invalidProjectConfig": "8,4,5",
        "verifiedSales": 20,
        "externalId": null,
        "highScoreRatio": 0.0,
        "isAdv": false,
        "cityName": "上海",
        "cityId": 321,
        "productCode": "1000480",
        "productName": "优享窝沟-限上海"
    },
    {
        "id": 94035,
        "externalOfficeCode": "SOC3122E97310F35C490F73FCAB3D5F9",
        "name": "华齿沪齿口腔门诊部",
        "address": "杨浦区江浦路2143路",
        "contactPhone": "02155961181",
        "picUrl": "https://pic5.40017.cn/i/ori/1GYFiJWBTGw.jpg",
        "intro": "",
        "workTime": "9：00-12：00，14：00-18：00",
        "distanceKm": null,
        "remark": "",
        "customTag": "",
        "qualityGrade": false,
        "demotionRank": 0,
        "invalidProjectConfig": "8,4,5",
        "verifiedSales": 15,
        "externalId": null,
        "highScoreRatio": 0.0,
        "isAdv": false,
        "cityName": "上海",
        "cityId": 321,
        "productCode": "1000480",
        "productName": "优享窝沟-限上海"
    },
    {
        "id": 94046,
        "externalOfficeCode": "SOFC15BF89BF513853BDF912EC805D27",
        "name": "华齿皓准口腔门诊部",
        "address": "金山区朱泾镇临源街396号（靠近朱泾第二小学东校区）",
        "contactPhone": "02157360383",
        "picUrl": "https://pic5.40017.cn/i/ori/1GYFiJWBTGw.jpg",
        "intro": "",
        "workTime": "9：00-12：00，14：00-18：00",
        "distanceKm": null,
        "remark": "",
        "customTag": "",
        "qualityGrade": false,
        "demotionRank": 0,
        "invalidProjectConfig": "8,4,5",
        "verifiedSales": 15,
        "externalId": null,
        "highScoreRatio": 0.0,
        "isAdv": false,
        "cityName": "上海",
        "cityId": 321,
        "productCode": "1000480",
        "productName": "优享窝沟-限上海"
    },
    {
        "id": 94042,
        "externalOfficeCode": "SOAF60A0D26A453DCF84E89C2AEFD445",
        "name": "华齿皓齿口腔门诊部",
        "address": "徐汇区上中西路236号（距天等路100米）",
        "contactPhone": "02154410678",
        "picUrl": "https://pic5.40017.cn/i/ori/1GYFiJWBTGw.jpg",
        "intro": "",
        "workTime": "9：00-12：00，14：00-18：00",
        "distanceKm": null,
        "remark": "",
        "customTag": "",
        "qualityGrade": false,
        "demotionRank": 0,
        "invalidProjectConfig": "8,4,5",
        "verifiedSales": 24,
        "externalId": null,
        "highScoreRatio": 0.0,
        "isAdv": false,
        "cityName": "上海",
        "cityId": 321,
        "productCode": "1000480",
        "productName": "优享窝沟-限上海"
    },
    {
        "id": 93988,
        "externalOfficeCode": "SOCC0CC41BC5C2389990B15EC37D59E0",
        "name": "弘晟口腔门诊",
        "address": "上海市浦东新区秋岚路104-114号2层",
        "contactPhone": "4009696189",
        "picUrl": "https://pic5.40017.cn/i/ori/1GRTWhPsq5O.jpg",
        "intro": "",
        "workTime": "9：00-11：00，13：30-17：00",
        "distanceKm": null,
        "remark": "",
        "customTag": "",
        "qualityGrade": false,
        "demotionRank": 0,
        "invalidProjectConfig": "",
        "verifiedSales": 16,
        "externalId": null,
        "highScoreRatio": 0.0,
        "isAdv": false,
        "cityName": "上海",
        "cityId": 321,
        "productCode": "1000480",
        "productName": "优享窝沟-限上海"
    },
    {
        "id": 93991,
        "externalOfficeCode": "SO74E297001E83370BA372C4F5A57BE1",
        "name": "旺达口腔门诊",
        "address": "上海市浦东新区宣桥镇宣中路500弄",
        "contactPhone": "4009696189",
        "picUrl": "https://pic5.40017.cn/i/ori/1GRTWhPsq5O.jpg",
        "intro": "",
        "workTime": "9：00-11：00，13：30-17：00",
        "distanceKm": null,
        "remark": "",
        "customTag": "",
        "qualityGrade": false,
        "demotionRank": 0,
        "invalidProjectConfig": "",
        "verifiedSales": 23,
        "externalId": null,
        "highScoreRatio": 0.0,
        "isAdv": false,
        "cityName": "上海",
        "cityId": 321,
        "productCode": "1000480",
        "productName": "优享窝沟-限上海"
    },
    {
        "id": 94039,
        "externalOfficeCode": "SO5F04456A42813DA3B74A2F5E814C66",
        "name": "明皓口腔门诊部",
        "address": "浦东新区三林路1498-1518号",
        "contactPhone": "02150857516",
        "picUrl": "https://pic5.40017.cn/i/ori/1GYFiJWBTGw.jpg",
        "intro": "",
        "workTime": "9：00-12：00，14：00-18：00",
        "distanceKm": null,
        "remark": "",
        "customTag": "",
        "qualityGrade": false,
        "demotionRank": 0,
        "invalidProjectConfig": "8,4,5",
        "verifiedSales": 46,
        "externalId": null,
        "highScoreRatio": 1.0,
        "isAdv": false,
        "cityName": "上海",
        "cityId": 321,
        "productCode": "1000480",
        "productName": "优享窝沟-限上海"
    },
    {
        "id": 93986,
        "externalOfficeCode": "SO09423E4B6FC631DA84DC10E31225F3",
        "name": "永菊口腔门诊",
        "address": "上海市浦东新区惠南镇城东路252号2层",
        "contactPhone": "4009696189",
        "picUrl": "https://pic5.40017.cn/i/ori/1GRTWhPsq5O.jpg",
        "intro": "",
        "workTime": "9：00-11：00，13：30-17：00",
        "distanceKm": null,
        "remark": "",
        "customTag": "",
        "qualityGrade": false,
        "demotionRank": 0,
        "invalidProjectConfig": "",
        "verifiedSales": 44,
        "externalId": null,
        "highScoreRatio": 0.0,
        "isAdv": false,
        "cityName": "上海",
        "cityId": 321,
        "productCode": "1000480",
        "productName": "优享窝沟-限上海"
    },
    {
        "id": 93990,
        "externalOfficeCode": "SO3C1A394B7B5E3C18A9412296D5ECE1",
        "name": "煜波口腔门诊",
        "address": "上海市闵行区碧江路333、335号",
        "contactPhone": "4009696189",
        "picUrl": "https://pic5.40017.cn/i/ori/1GRTWhPsq5O.jpg",
        "intro": "",
        "workTime": "9：00-11：00，13：30-17：00",
        "distanceKm": null,
        "remark": "",
        "customTag": "",
        "qualityGrade": false,
        "demotionRank": 0,
        "invalidProjectConfig": "",
        "verifiedSales": 16,
        "externalId": null,
        "highScoreRatio": 0.0,
        "isAdv": false,
        "cityName": "上海",
        "cityId": 321,
        "productCode": "1000480",
        "productName": "优享窝沟-限上海"
    },
    {
        "id": 94033,
        "externalOfficeCode": "SO8DEC5318349E37DFBEFAF3D9B51F66",
        "name": "爱齿口腔门诊部",
        "address": "杨浦区平凉路1127号（距眉州路180米）",
        "contactPhone": "02165195549",
        "picUrl": "https://pic5.40017.cn/i/ori/1GYFiJWBTGw.jpg",
        "intro": "",
        "workTime": "9：00-12：00，14：00-18：00",
        "distanceKm": null,
        "remark": "",
        "customTag": "",
        "qualityGrade": false,
        "demotionRank": 0,
        "invalidProjectConfig": "8,4,5",
        "verifiedSales": 16,
        "externalId": null,
        "highScoreRatio": 0.0,
        "isAdv": false,
        "cityName": "上海",
        "cityId": 321,
        "productCode": "1000480",
        "productName": "优享窝沟-限上海"
    },
    {
        "id": 93992,
        "externalOfficeCode": "SOE2E11A1466AB330281D89B8ED3C56E",
        "name": "珺仁口腔门诊",
        "address": "上海市浦东新区秀沿路2584号一层",
        "contactPhone": "4009696189",
        "picUrl": "https://pic5.40017.cn/i/ori/1GRTWhPsq5O.jpg",
        "intro": "",
        "workTime": "9：00-11：00，13：30-17：00",
        "distanceKm": null,
        "remark": "",
        "customTag": "",
        "qualityGrade": false,
        "demotionRank": 0,
        "invalidProjectConfig": "",
        "verifiedSales": 22,
        "externalId": null,
        "highScoreRatio": 0.0,
        "isAdv": false,
        "cityName": "上海",
        "cityId": 321,
        "productCode": "1000480",
        "productName": "优享窝沟-限上海"
    },
    {
        "id": 87332,
        "externalOfficeCode": "SO4822C14B51B8366FB01268E29F058B",
        "name": "维乐口腔 埃齐门诊",
        "address": "上海市静安区昌平路535号",
        "contactPhone": "4008889901",
        "picUrl": "https://pic5.40017.cn/i/ori/1wuetvCeGcw.png",
        "intro": "",
        "workTime": "9：30-17：00",
        "distanceKm": null,
        "remark": "关爱口腔健康，绽放自信笑容",
        "customTag": "",
        "qualityGrade": false,
        "demotionRank": 0,
        "invalidProjectConfig": "",
        "verifiedSales": 115,
        "externalId": null,
        "highScoreRatio": 1.0,
        "isAdv": false,
        "cityName": "上海",
        "cityId": 321,
        "productCode": "1000480",
        "productName": "优享窝沟-限上海"
    },
    {
        "id": 87331,
        "externalOfficeCode": "SOFA790664998334D38E99C9F0CF4B23",
        "name": "维乐口腔 奥美门诊",
        "address": "上海市静安区长寿路1051、1053号二楼",
        "contactPhone": "4008889901",
        "picUrl": "https://pic5.40017.cn/i/ori/1wuetvCeGcw.png",
        "intro": "",
        "workTime": "9：30-17：00",
        "distanceKm": null,
        "remark": "关爱口腔健康，绽放自信笑容",
        "customTag": "",
        "qualityGrade": false,
        "demotionRank": 0,
        "invalidProjectConfig": "",
        "verifiedSales": 100,
        "externalId": null,
        "highScoreRatio": 1.0,
        "isAdv": false,
        "cityName": "上海",
        "cityId": 321,
        "productCode": "1000480",
        "productName": "优享窝沟-限上海"
    },
    {
        "id": 87333,
        "externalOfficeCode": "SO0D0388CD927532C0915248C227789F",
        "name": "维乐口腔 德光门诊",
        "address": "上海市虹桥路536号1-2层门牌号510号",
        "contactPhone": "4008889901",
        "picUrl": "https://pic5.40017.cn/i/ori/1wuetvCeGcw.png",
        "intro": "",
        "workTime": "9：30-17：00",
        "distanceKm": null,
        "remark": "关爱口腔健康，绽放自信笑容",
        "customTag": "",
        "qualityGrade": false,
        "demotionRank": 0,
        "invalidProjectConfig": "",
        "verifiedSales": 116,
        "externalId": null,
        "highScoreRatio": 1.0,
        "isAdv": false,
        "cityName": "上海",
        "cityId": 321,
        "productCode": "1000480",
        "productName": "优享窝沟-限上海"
    },
    {
        "id": 87330,
        "externalOfficeCode": "SOCC66DC4F42A23DB9935A38E66412D1",
        "name": "维乐口腔 格林门诊",
        "address": "上海市长宁区荣华东道96号",
        "contactPhone": "4008889901",
        "picUrl": "https://pic5.40017.cn/i/ori/1wuetvCeGcw.png",
        "intro": "",
        "workTime": "9：30-17：00",
        "distanceKm": null,
        "remark": "关爱口腔健康，绽放自信笑容",
        "customTag": "",
        "qualityGrade": false,
        "demotionRank": 0,
        "invalidProjectConfig": "",
        "verifiedSales": 147,
        "externalId": null,
        "highScoreRatio": 1.0,
        "isAdv": false,
        "cityName": "上海",
        "cityId": 321,
        "productCode": "1000480",
        "productName": "优享窝沟-限上海"
    },
    {
        "id": 87335,
        "externalOfficeCode": "SO191AC71BAE8B37AD96BDF61A0A2622",
        "name": "维乐口腔 美达门诊",
        "address": "上海市普陀区延长西路586号201、202室",
        "contactPhone": "4008889901",
        "picUrl": "https://pic5.40017.cn/i/ori/1wuetvCeGcw.png",
        "intro": "",
        "workTime": "9：30-17：00",
        "distanceKm": null,
        "remark": "关爱口腔健康，绽放自信笑容",
        "customTag": "",
        "qualityGrade": false,
        "demotionRank": 0,
        "invalidProjectConfig": "",
        "verifiedSales": 114,
        "externalId": null,
        "highScoreRatio": 1.0,
        "isAdv": false,
        "cityName": "上海",
        "cityId": 321,
        "productCode": "1000480",
        "productName": "优享窝沟-限上海"
    },
    {
        "id": 93987,
        "externalOfficeCode": "SO677B71A2FFC33DE29D132E3C166A28",
        "name": "美尔琪口腔门诊",
        "address": "上海市浦东新区庆荣路173号2楼",
        "contactPhone": "4009696189",
        "picUrl": "https://pic5.40017.cn/i/ori/1GRTWhPsq5O.jpg",
        "intro": "",
        "workTime": "9：00-11：00，13：30-17：00",
        "distanceKm": null,
        "remark": "",
        "customTag": "",
        "qualityGrade": false,
        "demotionRank": 0,
        "invalidProjectConfig": "",
        "verifiedSales": 22,
        "externalId": null,
        "highScoreRatio": 0.0,
        "isAdv": false,
        "cityName": "上海",
        "cityId": 321,
        "productCode": "1000480",
        "productName": "优享窝沟-限上海"
    },
    {
        "id": 93993,
        "externalOfficeCode": "SOBAF9686C415D3130A92E507708311B",
        "name": "芳芳口腔门诊",
        "address": "上海市浦东新区平度路104-106号",
        "contactPhone": "4009696189",
        "picUrl": "https://pic5.40017.cn/i/ori/1GRTWhPsq5O.jpg",
        "intro": "",
        "workTime": "9：00-11：00，13：30-17：00",
        "distanceKm": null,
        "remark": "",
        "customTag": "",
        "qualityGrade": false,
        "demotionRank": 0,
        "invalidProjectConfig": "",
        "verifiedSales": 11,
        "externalId": null,
        "highScoreRatio": 0.0,
        "isAdv": false,
        "cityName": "上海",
        "cityId": 321,
        "productCode": "1000480",
        "productName": "优享窝沟-限上海"
    },
    {
        "id": 93989,
        "externalOfficeCode": "SO27D264C223713F7AA1AB2F3CBEB1B1",
        "name": "茂齿口腔门诊",
        "address": "上海市浦东新区新园路98弄1号285室",
        "contactPhone": "4009696189",
        "picUrl": "https://pic5.40017.cn/i/ori/1GRTWhPsq5O.jpg",
        "intro": "",
        "workTime": "9：00-11：00，13：30-17：00",
        "distanceKm": null,
        "remark": "",
        "customTag": "",
        "qualityGrade": false,
        "demotionRank": 0,
        "invalidProjectConfig": "",
        "verifiedSales": 20,
        "externalId": null,
        "highScoreRatio": 0.0,
        "isAdv": false,
        "cityName": "上海",
        "cityId": 321,
        "productCode": "1000480",
        "productName": "优享窝沟-限上海"
    },
    {
        "id": 93994,
        "externalOfficeCode": "SO07B55FE5271C31358E493D52DBD407",
        "name": "轩尔口腔门诊",
        "address": "上海市金山区城河路403-407号1-2层",
        "contactPhone": "4009696189",
        "picUrl": "https://pic5.40017.cn/i/ori/1GRTWhPsq5O.jpg",
        "intro": "",
        "workTime": "9：00-11：00，13：30-17：00",
        "distanceKm": null,
        "remark": "",
        "customTag": "",
        "qualityGrade": false,
        "demotionRank": 0,
        "invalidProjectConfig": "",
        "verifiedSales": 27,
        "externalId": null,
        "highScoreRatio": 0.0,
        "isAdv": false,
        "cityName": "上海",
        "cityId": 321,
        "productCode": "1000480",
        "productName": "优享窝沟-限上海"
    },
    {
        "id": 93996,
        "externalOfficeCode": "SOD6AE3C59DD3831E3AFF1724F62E9E1",
        "name": "鑫湟口腔门诊",
        "address": "上海市浦东新区惠南镇听悦路1333号1层103",
        "contactPhone": "4009696189",
        "picUrl": "https://pic5.40017.cn/i/ori/1GRTWhPsq5O.jpg",
        "intro": "",
        "workTime": "9：00-11：00，13：30-17：00",
        "distanceKm": null,
        "remark": "",
        "customTag": "",
        "qualityGrade": false,
        "demotionRank": 0,
        "invalidProjectConfig": "",
        "verifiedSales": 22,
        "externalId": null,
        "highScoreRatio": 1.0,
        "isAdv": false,
        "cityName": "上海",
        "cityId": 321,
        "productCode": "1000480",
        "productName": "优享窝沟-限上海"
    },
    {
        "id": 93985,
        "externalOfficeCode": "SO42AAD24423AC34E5A8340C8E3F3962",
        "name": "鑫齿口腔门诊",
        "address": "上海市浦东新区金高路1050-4号",
        "contactPhone": "4009696189",
        "picUrl": "https://pic5.40017.cn/i/ori/1GRTWhPsq5O.jpg",
        "intro": "",
        "workTime": "9：00-11：00，13：30-17：00",
        "distanceKm": null,
        "remark": "",
        "customTag": "",
        "qualityGrade": false,
        "demotionRank": 0,
        "invalidProjectConfig": "",
        "verifiedSales": 25,
        "externalId": null,
        "highScoreRatio": 0.0,
        "isAdv": false,
        "cityName": "上海",
        "cityId": 321,
        "productCode": "1000480",
        "productName": "优享窝沟-限上海"
    },
    {
        "id": 93997,
        "externalOfficeCode": "SOA04FFB86ECB234F1A0A183DA24EAC2",
        "name": "鑫齿鑫福口腔门诊",
        "address": "上海市浦东新区清溪路200",
        "contactPhone": "4009696189",
        "picUrl": "https://pic5.40017.cn/i/ori/1GRTWhPsq5O.jpg",
        "intro": "",
        "workTime": "9：00-11：00，13：30-17：00",
        "distanceKm": null,
        "remark": "",
        "customTag": "",
        "qualityGrade": false,
        "demotionRank": 0,
        "invalidProjectConfig": "",
        "verifiedSales": 17,
        "externalId": null,
        "highScoreRatio": 0.0,
        "isAdv": false,
        "cityName": "上海",
        "cityId": 321,
        "productCode": "1000480",
        "productName": "优享窝沟-限上海"
    },
    {
        "id": 93995,
        "externalOfficeCode": "SO7AF777B664623D5CBD11C8EFFB6496",
        "name": "鑫齿鼎美口腔",
        "address": "上海市浦东新区金高路1744号1层",
        "contactPhone": "4009696189",
        "picUrl": "https://pic5.40017.cn/i/ori/1GRTWhPsq5O.jpg",
        "intro": "",
        "workTime": "9：00-11：00，13：30-17：00",
        "distanceKm": null,
        "remark": "",
        "customTag": "",
        "qualityGrade": false,
        "demotionRank": 0,
        "invalidProjectConfig": "",
        "verifiedSales": 16,
        "externalId": null,
        "highScoreRatio": 0.0,
        "isAdv": false,
        "cityName": "上海",
        "cityId": 321,
        "productCode": "1000480",
        "productName": "优享窝沟-限上海"
    },
    {
        "id": 94034,
        "externalOfficeCode": "SO4F5D79783ABC31E99CA642A7A6D180",
        "name": "长康口腔门诊部",
        "address": "杨浦区长阳路1945-1949号（距双阳路50米）",
        "contactPhone": "02165693370",
        "picUrl": "https://pic5.40017.cn/i/ori/1GYFiJWBTGw.jpg",
        "intro": "",
        "workTime": "9：00-12：00，14：00-18：00",
        "distanceKm": null,
        "remark": "",
        "customTag": "",
        "qualityGrade": false,
        "demotionRank": 0,
        "invalidProjectConfig": "8,4,5",
        "verifiedSales": 20,
        "externalId": null,
        "highScoreRatio": 0.0,
        "isAdv": false,
        "cityName": "上海",
        "cityId": 321,
        "productCode": "1000480",
        "productName": "优享窝沟-限上海"
    },
    {
        "id": 87383,
        "externalOfficeCode": "SOCDA6D68D9B9B3277BA37345B653DD3",
        "name": "上海泰康拜博万尔口腔门诊部",
        "address": "上海市闵行区申长路988弄虹桥万科中心商场2层T2-203-205号单元",
        "contactPhone": "02123301211",
        "picUrl": "https://pic5.40017.cn/i/ori/1wumsh1qQW4.png",
        "intro": "",
        "workTime": "9:30-17:00",
        "distanceKm": null,
        "remark": "关爱口腔健康，绽放自信笑容",
        "customTag": "",
        "qualityGrade": false,
        "demotionRank": 1,
        "invalidProjectConfig": "",
        "verifiedSales": 195,
        "externalId": null,
        "highScoreRatio": 1.0,
        "isAdv": false,
        "cityName": "上海",
        "cityId": 321,
        "productCode": "1000480",
        "productName": "优享窝沟-限上海"
    },
    {
        "id": 87390,
        "externalOfficeCode": "SO86EF1563702E3701AAF1848DE214F2",
        "name": "上海泰康拜博信尔口腔门诊部",
        "address": "浦东新区永泰路1058弄1-26号三林印象城302室",
        "contactPhone": "02123301211",
        "picUrl": "https://pic5.40017.cn/i/ori/1wumsh1qQW4.png",
        "intro": "",
        "workTime": "9:30-17:00",
        "distanceKm": null,
        "remark": "关爱口腔健康，绽放自信笑容",
        "customTag": "",
        "qualityGrade": false,
        "demotionRank": 1,
        "invalidProjectConfig": "",
        "verifiedSales": 293,
        "externalId": null,
        "highScoreRatio": 1.0,
        "isAdv": false,
        "cityName": "上海",
        "cityId": 321,
        "productCode": "1000480",
        "productName": "优享窝沟-限上海"
    },
    {
        "id": 87387,
        "externalOfficeCode": "SOD6361A81AED13EADB0D4FE16407DE8",
        "name": "上海泰康拜博口腔医院",
        "address": "上海市黄浦区西藏中路18号港陆广场4楼、5楼、六楼",
        "contactPhone": "02123301211",
        "picUrl": "https://pic5.40017.cn/i/ori/1wumsh1qQW4.png",
        "intro": "",
        "workTime": "9:30-17:00",
        "distanceKm": null,
        "remark": "关爱口腔健康，绽放自信笑容",
        "customTag": "",
        "qualityGrade": false,
        "demotionRank": 1,
        "invalidProjectConfig": "",
        "verifiedSales": 273,
        "externalId": null,
        "highScoreRatio": 1.0,
        "isAdv": false,
        "cityName": "上海",
        "cityId": 321,
        "productCode": "1000480",
        "productName": "优享窝沟-限上海"
    },
    {
        "id": 87389,
        "externalOfficeCode": "SO6B31264993263E5D97DFF0FBD85EA4",
        "name": "上海泰康拜博悦尔口腔门诊部",
        "address": "上海市嘉定区白银路288弄77号501室",
        "contactPhone": "02123301211",
        "picUrl": "https://pic5.40017.cn/i/ori/1wumsh1qQW4.png",
        "intro": "",
        "workTime": "9:30-17:00",
        "distanceKm": null,
        "remark": "关爱口腔健康，绽放自信笑容",
        "customTag": "",
        "qualityGrade": false,
        "demotionRank": 1,
        "invalidProjectConfig": "",
        "verifiedSales": 220,
        "externalId": null,
        "highScoreRatio": 1.0,
        "isAdv": false,
        "cityName": "上海",
        "cityId": 321,
        "productCode": "1000480",
        "productName": "优享窝沟-限上海"
    },
    {
        "id": 87382,
        "externalOfficeCode": "SO6FEF7D37D2ED341691EBDFE0886830",
        "name": "上海泰康拜博松尔口腔门诊部",
        "address": "上海市松江区光星路1572号",
        "contactPhone": "02123301211",
        "picUrl": "https://pic5.40017.cn/i/ori/1wumsh1qQW4.png",
        "intro": "",
        "workTime": "9:30-17:00",
        "distanceKm": null,
        "remark": "关爱口腔健康，绽放自信笑容",
        "customTag": "",
        "qualityGrade": false,
        "demotionRank": 1,
        "invalidProjectConfig": "",
        "verifiedSales": 263,
        "externalId": null,
        "highScoreRatio": 1.0,
        "isAdv": false,
        "cityName": "上海",
        "cityId": 321,
        "productCode": "1000480",
        "productName": "优享窝沟-限上海"
    },
    {
        "id": 87366,
        "externalOfficeCode": "SOD23F6F0E7A033A2EB59DD190AD97D4",
        "name": "上海泰康拜博柏尔口腔门诊部",
        "address": "上海市浦东新区迎春路1275号201-207（近紫槐路）",
        "contactPhone": "02123301211",
        "picUrl": "https://pic5.40017.cn/i/ori/1wumsh1qQW4.png",
        "intro": "",
        "workTime": "9:30-17:00",
        "distanceKm": null,
        "remark": "关爱口腔健康，绽放自信笑容",
        "customTag": "",
        "qualityGrade": false,
        "demotionRank": 1,
        "invalidProjectConfig": "",
        "verifiedSales": 244,
        "externalId": null,
        "highScoreRatio": 1.0,
        "isAdv": false,
        "cityName": "上海",
        "cityId": 321,
        "productCode": "1000480",
        "productName": "优享窝沟-限上海"
    },
    {
        "id": 87393,
        "externalOfficeCode": "SOBE6D39DCEC763CEDAD1F6F5800A222",
        "name": "上海泰康拜博淞耀口腔医院",
        "address": "上海市杨浦区淞沪路234号201-209室",
        "contactPhone": "02123301211",
        "picUrl": "https://pic5.40017.cn/i/ori/1wumsh1qQW4.png",
        "intro": "",
        "workTime": "9:30-17:00",
        "distanceKm": null,
        "remark": "关爱口腔健康，绽放自信笑容",
        "customTag": "",
        "qualityGrade": false,
        "demotionRank": 1,
        "invalidProjectConfig": "",
        "verifiedSales": 228,
        "externalId": null,
        "highScoreRatio": 1.0,
        "isAdv": false,
        "cityName": "上海",
        "cityId": 321,
        "productCode": "1000480",
        "productName": "优享窝沟-限上海"
    },
    {
        "id": 87394,
        "externalOfficeCode": "SOC46EE1B68FDB3B57B03BFE3ABBFAA2",
        "name": "上海泰康拜博臻尔口腔诊所",
        "address": "上海市松江区广富林路1788弄1号3层L326号单元",
        "contactPhone": "02123301211",
        "picUrl": "https://pic5.40017.cn/i/ori/1wumsh1qQW4.png",
        "intro": "",
        "workTime": "9:30-17:00",
        "distanceKm": null,
        "remark": "关爱口腔健康，绽放自信笑容",
        "customTag": "",
        "qualityGrade": false,
        "demotionRank": 1,
        "invalidProjectConfig": "",
        "verifiedSales": 244,
        "externalId": null,
        "highScoreRatio": 1.0,
        "isAdv": false,
        "cityName": "上海",
        "cityId": 321,
        "productCode": "1000480",
        "productName": "优享窝沟-限上海"
    },
    {
        "id": 87370,
        "externalOfficeCode": "SO945A4F9904C7324E83892640AF581A",
        "name": "上海泰康拜博达尔口腔门诊部",
        "address": "上海市浦东新区沪南公路3439弄25号（万达美食街）",
        "contactPhone": "02123301211",
        "picUrl": "https://pic5.40017.cn/i/ori/1wumsh1qQW4.png",
        "intro": "",
        "workTime": "9:30-17:00",
        "distanceKm": null,
        "remark": "关爱口腔健康，绽放自信笑容",
        "customTag": "",
        "qualityGrade": false,
        "demotionRank": 1,
        "invalidProjectConfig": "",
        "verifiedSales": 528,
        "externalId": null,
        "highScoreRatio": 1.0,
        "isAdv": false,
        "cityName": "上海",
        "cityId": 321,
        "productCode": "1000480",
        "productName": "优享窝沟-限上海"
    },
    {
        "id": 88928,
        "externalOfficeCode": "SOD8BE401CF7973703862225D48FB675",
        "name": "上海瑞凡口腔门诊部",
        "address": "上海市奉贤区南桥镇南奉公路9755号",
        "contactPhone": "4007788190",
        "picUrl": "https://pic5.40017.cn/i/ori/1wueqxlrlEA.png",
        "intro": "",
        "workTime": "9：00-17：00",
        "distanceKm": null,
        "remark": "",
        "customTag": "",
        "qualityGrade": false,
        "demotionRank": 1,
        "invalidProjectConfig": "",
        "verifiedSales": 63,
        "externalId": null,
        "highScoreRatio": 0.0,
        "isAdv": false,
        "cityName": "上海",
        "cityId": 321,
        "productCode": "1000480",
        "productName": "优享窝沟-限上海"
    },
    {
        "id": 92246,
        "externalOfficeCode": "SOABE4664A985530A2B0AD08C7FF36D6",
        "name": "上海鼎植九福口腔门诊部有限公司",
        "address": "上海市闵行区沪星路105号2幢1楼（凯德七宝停车场旁）",
        "contactPhone": "021-52210030",
        "picUrl": "https://pic5.40017.cn/i/ori/1E5LiyvVwaI.png",
        "intro": "",
        "workTime": "9：30-18：00",
        "distanceKm": null,
        "remark": "",
        "customTag": "",
        "qualityGrade": false,
        "demotionRank": 1,
        "invalidProjectConfig": "",
        "verifiedSales": 23,
        "externalId": null,
        "highScoreRatio": 0.0,
        "isAdv": false,
        "cityName": "上海",
        "cityId": 321,
        "productCode": "1000480",
        "productName": "优享窝沟-限上海"
    },
    {
        "id": 92245,
        "externalOfficeCode": "SO6877D202E6AC3748AED8E99CD9D638",
        "name": "上海鼎植八八口腔门诊部有限公司",
        "address": "上海市浦东新区浦东南路1078号1088广场5F-507室",
        "contactPhone": "021-50365057",
        "picUrl": "https://pic5.40017.cn/i/ori/1E5LiyvVwaI.png",
        "intro": "",
        "workTime": "9：30-18：00",
        "distanceKm": null,
        "remark": "",
        "customTag": "",
        "qualityGrade": false,
        "demotionRank": 1,
        "invalidProjectConfig": "",
        "verifiedSales": 33,
        "externalId": null,
        "highScoreRatio": 1.0,
        "isAdv": false,
        "cityName": "上海",
        "cityId": 321,
        "productCode": "1000480",
        "productName": "优享窝沟-限上海"
    },
    {
        "id": 92248,
        "externalOfficeCode": "SOE1772BC1FF3134849C0E8B30BE0947",
        "name": "上海鼎植有为口腔诊所有限公司",
        "address": "上海市长宁区仙霞西路88号3层G05-F03-1-302室",
        "contactPhone": "021-64680582",
        "picUrl": "https://pic5.40017.cn/i/ori/1E5LiyvVwaI.png",
        "intro": "",
        "workTime": "9：30-18：00",
        "distanceKm": null,
        "remark": "",
        "customTag": "",
        "qualityGrade": false,
        "demotionRank": 1,
        "invalidProjectConfig": "",
        "verifiedSales": 45,
        "externalId": null,
        "highScoreRatio": 1.0,
        "isAdv": false,
        "cityName": "上海",
        "cityId": 321,
        "productCode": "1000480",
        "productName": "优享窝沟-限上海"
    },
    {
        "id": 92244,
        "externalOfficeCode": "SO748C3385CC093FE6A37EA24B133112",
        "name": "上海鼎植米域口腔诊所有限公司",
        "address": "上海市长宁区愚园路1398号3F-02室",
        "contactPhone": "021-62088788",
        "picUrl": "https://pic5.40017.cn/i/ori/1E5LiyvVwaI.png",
        "intro": "",
        "workTime": "9：30-18：00",
        "distanceKm": null,
        "remark": "",
        "customTag": "",
        "qualityGrade": false,
        "demotionRank": 1,
        "invalidProjectConfig": "",
        "verifiedSales": 24,
        "externalId": null,
        "highScoreRatio": 0.0,
        "isAdv": false,
        "cityName": "上海",
        "cityId": 321,
        "productCode": "1000480",
        "productName": "优享窝沟-限上海"
    },
    {
        "id": 92243,
        "externalOfficeCode": "SO6847F49C8015BA376F",
        "name": "上海鼎植黎强口腔门诊部有限公司",
        "address": "上海市黄浦区淮海中路1号701室、801室",
        "contactPhone": "021-63333066",
        "picUrl": "https://pic5.40017.cn/i/ori/1E5LiyvVwaI.png",
        "intro": "",
        "workTime": "9：30-18：00",
        "distanceKm": null,
        "remark": "",
        "customTag": "",
        "qualityGrade": false,
        "demotionRank": 1,
        "invalidProjectConfig": "",
        "verifiedSales": 7,
        "externalId": null,
        "highScoreRatio": 0.0,
        "isAdv": false,
        "cityName": "上海",
        "cityId": 321,
        "productCode": "1000480",
        "productName": "优享窝沟-限上海"
    },
    {
        "id": 87360,
        "externalOfficeCode": "SO017CFDFB730E3D87AFAAC75B8E8495",
        "name": "华尔康中博口腔",
        "address": "上海市青浦区青湖路782_798号",
        "contactPhone": "19352123459",
        "picUrl": "https://pic5.40017.cn/i/ori/1wuekOVgrUQ.png",
        "intro": "",
        "workTime": "9：00-17：00",
        "distanceKm": null,
        "remark": "关爱口腔健康，绽放自信笑容",
        "customTag": "",
        "qualityGrade": false,
        "demotionRank": 1,
        "invalidProjectConfig": "",
        "verifiedSales": 139,
        "externalId": null,
        "highScoreRatio": 0.0,
        "isAdv": false,
        "cityName": "上海",
        "cityId": 321,
        "productCode": "1000480",
        "productName": "优享窝沟-限上海"
    },
    {
        "id": 87362,
        "externalOfficeCode": "SOF6761CDE72243112B027C34EEB8018",
        "name": "华尔康仁川口腔",
        "address": "浦东新区川沙路4807-4621号(单号)1幢1层B区、2层B区",
        "contactPhone": "19352123459",
        "picUrl": "https://pic5.40017.cn/i/ori/1wuekOVgrUQ.png",
        "intro": "",
        "workTime": "9：00-17：00",
        "distanceKm": null,
        "remark": "关爱口腔健康，绽放自信笑容",
        "customTag": "",
        "qualityGrade": false,
        "demotionRank": 1,
        "invalidProjectConfig": "",
        "verifiedSales": 607,
        "externalId": null,
        "highScoreRatio": 1.0,
        "isAdv": false,
        "cityName": "上海",
        "cityId": 321,
        "productCode": "1000480",
        "productName": "优享窝沟-限上海"
    },
    {
        "id": 87355,
        "externalOfficeCode": "SO95EFADCBE25D361FA7C8C40572200C",
        "name": "华尔康佳乐口腔",
        "address": "中国(上海)自由贸易试验区浦东大道1848号(临)一层",
        "contactPhone": "19352123459",
        "picUrl": "https://pic5.40017.cn/i/ori/1wuekOVgrUQ.png",
        "intro": "",
        "workTime": "9：00-17：00",
        "distanceKm": null,
        "remark": "关爱口腔健康，绽放自信笑容",
        "customTag": "",
        "qualityGrade": false,
        "demotionRank": 1,
        "invalidProjectConfig": "",
        "verifiedSales": 92,
        "externalId": null,
        "highScoreRatio": 1.0,
        "isAdv": false,
        "cityName": "上海",
        "cityId": 321,
        "productCode": "1000480",
        "productName": "优享窝沟-限上海"
    },
    {
        "id": 87354,
        "externalOfficeCode": "SO297984F147B333E39B90E11C2345E6",
        "name": "华尔康佳泉口腔",
        "address": "上海市宝山区高逸路7-29号1幢203、205、206、207室",
        "contactPhone": "19352123459",
        "picUrl": "https://pic5.40017.cn/i/ori/1wuekOVgrUQ.png",
        "intro": "",
        "workTime": "9：00-17：00",
        "distanceKm": null,
        "remark": "关爱口腔健康，绽放自信笑容",
        "customTag": "",
        "qualityGrade": false,
        "demotionRank": 1,
        "invalidProjectConfig": "",
        "verifiedSales": 11,
        "externalId": null,
        "highScoreRatio": 0.0,
        "isAdv": false,
        "cityName": "上海",
        "cityId": 321,
        "productCode": "1000480",
        "productName": "优享窝沟-限上海"
    },
    {
        "id": 87358,
        "externalOfficeCode": "SOE0D720151B5D31FFBB5008DB06A96C",
        "name": "华尔康宏齿口腔",
        "address": "宝山区年吉路100弄12号301、302、303、304、305",
        "contactPhone": "19352123459",
        "picUrl": "https://pic5.40017.cn/i/ori/1wuekOVgrUQ.png",
        "intro": "",
        "workTime": "9：00-17：00",
        "distanceKm": null,
        "remark": "关爱口腔健康，绽放自信笑容",
        "customTag": "",
        "qualityGrade": false,
        "demotionRank": 1,
        "invalidProjectConfig": "",
        "verifiedSales": 265,
        "externalId": null,
        "highScoreRatio": 1.0,
        "isAdv": false,
        "cityName": "上海",
        "cityId": 321,
        "productCode": "1000480",
        "productName": "优享窝沟-限上海"
    },
    {
        "id": 87356,
        "externalOfficeCode": "SO7D2BAED21E89333587FD610DD67D3D",
        "name": "华尔康德雅口腔",
        "address": "上海市闵行区古美西路313弄48号101-5至101-7室",
        "contactPhone": "19352123459",
        "picUrl": "https://pic5.40017.cn/i/ori/1wuekOVgrUQ.png",
        "intro": "",
        "workTime": "9：00-17：00",
        "distanceKm": null,
        "remark": "关爱口腔健康，绽放自信笑容",
        "customTag": "",
        "qualityGrade": false,
        "demotionRank": 1,
        "invalidProjectConfig": "",
        "verifiedSales": 164,
        "externalId": null,
        "highScoreRatio": 0.6,
        "isAdv": false,
        "cityName": "上海",
        "cityId": 321,
        "productCode": "1000480",
        "productName": "优享窝沟-限上海"
    },
    {
        "id": 87348,
        "externalOfficeCode": "SOB9195293B5E3399F8D9CACDD3CBAD2",
        "name": "华尔康新敦口腔",
        "address": "上海市松江区车墩镇影视路55-59号",
        "contactPhone": "19352123459",
        "picUrl": "https://pic5.40017.cn/i/ori/1wuekOVgrUQ.png",
        "intro": "",
        "workTime": "9：00-17：00",
        "distanceKm": null,
        "remark": "关爱口腔健康，绽放自信笑容",
        "customTag": "",
        "qualityGrade": false,
        "demotionRank": 1,
        "invalidProjectConfig": "",
        "verifiedSales": 150,
        "externalId": null,
        "highScoreRatio": 1.0,
        "isAdv": false,
        "cityName": "上海",
        "cityId": 321,
        "productCode": "1000480",
        "productName": "优享窝沟-限上海"
    },
    {
        "id": 87353,
        "externalOfficeCode": "SO0FA00E48D2F93A78AA75F81AF5EFE5",
        "name": "华尔康松江总院",
        "address": "上海市松江区乐都路188弄1-6号",
        "contactPhone": "19352123459",
        "picUrl": "https://pic5.40017.cn/i/ori/1wuekOVgrUQ.png",
        "intro": "",
        "workTime": "9：00-17：00",
        "distanceKm": null,
        "remark": "关爱口腔健康，绽放自信笑容",
        "customTag": "",
        "qualityGrade": false,
        "demotionRank": 1,
        "invalidProjectConfig": "",
        "verifiedSales": 390,
        "externalId": null,
        "highScoreRatio": 0.8333,
        "isAdv": false,
        "cityName": "上海",
        "cityId": 321,
        "productCode": "1000480",
        "productName": "优享窝沟-限上海"
    },
    {
        "id": 87350,
        "externalOfficeCode": "SOA816091CAA5C3AC997569448251151",
        "name": "华尔康毛日红口腔",
        "address": "上海市松江区新桥镇新镇街999弄997号1-2层",
        "contactPhone": "19352123459",
        "picUrl": "https://pic5.40017.cn/i/ori/1wuekOVgrUQ.png",
        "intro": "",
        "workTime": "9：00-17：00",
        "distanceKm": null,
        "remark": "关爱口腔健康，绽放自信笑容",
        "customTag": "",
        "qualityGrade": false,
        "demotionRank": 1,
        "invalidProjectConfig": "",
        "verifiedSales": 140,
        "externalId": null,
        "highScoreRatio": 0.0,
        "isAdv": false,
        "cityName": "上海",
        "cityId": 321,
        "productCode": "1000480",
        "productName": "优享窝沟-限上海"
    },
    {
        "id": 87349,
        "externalOfficeCode": "SOF0D923ACC2883662A415C422A43F21",
        "name": "华尔康王坚口腔",
        "address": "上海市松江区永丰街道玉树路2579号",
        "contactPhone": "19352123459",
        "picUrl": "https://pic5.40017.cn/i/ori/1wuekOVgrUQ.png",
        "intro": "",
        "workTime": "9：00-17：00",
        "distanceKm": null,
        "remark": "关爱口腔健康，绽放自信笑容",
        "customTag": "",
        "qualityGrade": false,
        "demotionRank": 1,
        "invalidProjectConfig": "",
        "verifiedSales": 181,
        "externalId": null,
        "highScoreRatio": 1.0,
        "isAdv": false,
        "cityName": "上海",
        "cityId": 321,
        "productCode": "1000480",
        "productName": "优享窝沟-限上海"
    },
    {
        "id": 87363,
        "externalOfficeCode": "SO4F1C7401026036D6931AB502652D02",
        "name": "华尔康皓志口腔",
        "address": "上海市松江区沪松公路1510号一层106、107室",
        "contactPhone": "19352123459",
        "picUrl": "https://pic5.40017.cn/i/ori/1wuekOVgrUQ.png",
        "intro": "",
        "workTime": "9：00-17：00",
        "distanceKm": null,
        "remark": "关爱口腔健康，绽放自信笑容",
        "customTag": "",
        "qualityGrade": false,
        "demotionRank": 1,
        "invalidProjectConfig": "",
        "verifiedSales": 125,
        "externalId": null,
        "highScoreRatio": 0.6667,
        "isAdv": false,
        "cityName": "上海",
        "cityId": 321,
        "productCode": "1000480",
        "productName": "优享窝沟-限上海"
    },
    {
        "id": 87351,
        "externalOfficeCode": "SOD2C172347A8B3249A7911A0AFDAE0E",
        "name": "华尔康知乐口腔",
        "address": "上海市松江区九亭镇九亭大街504号",
        "contactPhone": "19352123459",
        "picUrl": "https://pic5.40017.cn/i/ori/1wuekOVgrUQ.png",
        "intro": "",
        "workTime": "9：00-17：00",
        "distanceKm": null,
        "remark": "关爱口腔健康，绽放自信笑容",
        "customTag": "",
        "qualityGrade": false,
        "demotionRank": 1,
        "invalidProjectConfig": "",
        "verifiedSales": 146,
        "externalId": null,
        "highScoreRatio": 0.6667,
        "isAdv": false,
        "cityName": "上海",
        "cityId": 321,
        "productCode": "1000480",
        "productName": "优享窝沟-限上海"
    },
    {
        "id": 87359,
        "externalOfficeCode": "SO27AEFAD014643AFBAD23A7D39837F1",
        "name": "华尔康福鑫口腔",
        "address": "上海市虹口区东宝兴路915号底层、二层",
        "contactPhone": "19352123459",
        "picUrl": "https://pic5.40017.cn/i/ori/1wuekOVgrUQ.png",
        "intro": "",
        "workTime": "9：00-17：00",
        "distanceKm": null,
        "remark": "关爱口腔健康，绽放自信笑容",
        "customTag": "",
        "qualityGrade": false,
        "demotionRank": 1,
        "invalidProjectConfig": "",
        "verifiedSales": 17,
        "externalId": null,
        "highScoreRatio": 1.0,
        "isAdv": false,
        "cityName": "上海",
        "cityId": 321,
        "productCode": "1000480",
        "productName": "优享窝沟-限上海"
    },
    {
        "id": 87352,
        "externalOfficeCode": "SOE3D3C2F27AC03F15B4C28F1FF9185D",
        "name": "华尔康馨乐口腔",
        "address": "上海市闵行区七莘路2348号一楼、二楼",
        "contactPhone": "19352123459",
        "picUrl": "https://pic5.40017.cn/i/ori/1wuekOVgrUQ.png",
        "intro": "",
        "workTime": "9：00-17：00",
        "distanceKm": null,
        "remark": "关爱口腔健康，绽放自信笑容",
        "customTag": "",
        "qualityGrade": false,
        "demotionRank": 1,
        "invalidProjectConfig": "",
        "verifiedSales": 120,
        "externalId": null,
        "highScoreRatio": 1.0,
        "isAdv": false,
        "cityName": "上海",
        "cityId": 321,
        "productCode": "1000480",
        "productName": "优享窝沟-限上海"
    },
    {
        "id": 87347,
        "externalOfficeCode": "SOBE0EFD743863388DA5C46136682D74",
        "name": "华尔康麦芽口腔",
        "address": "上海市闵行区田林路1449号",
        "contactPhone": "19352123459",
        "picUrl": "https://pic5.40017.cn/i/ori/1wuekOVgrUQ.png",
        "intro": "",
        "workTime": "9：00-17：00",
        "distanceKm": null,
        "remark": "关爱口腔健康，绽放自信笑容",
        "customTag": "",
        "qualityGrade": false,
        "demotionRank": 1,
        "invalidProjectConfig": "",
        "verifiedSales": 75,
        "externalId": null,
        "highScoreRatio": 1.0,
        "isAdv": false,
        "cityName": "上海",
        "cityId": 321,
        "productCode": "1000480",
        "productName": "优享窝沟-限上海"
    },
    {
        "id": 87322,
        "externalOfficeCode": "SOD5FA0C84A8FD3D699A79D62BABE4B7",
        "name": "瑞伢美口腔连锁.博文口腔",
        "address": "上海市宝山区淞发路939号3楼",
        "contactPhone": "4007788190",
        "picUrl": "https://pic5.40017.cn/i/ori/1wueqxlrlEA.png",
        "intro": "",
        "workTime": "9：00-17：00",
        "distanceKm": null,
        "remark": "",
        "customTag": "",
        "qualityGrade": false,
        "demotionRank": 1,
        "invalidProjectConfig": "",
        "verifiedSales": 100,
        "externalId": null,
        "highScoreRatio": 1.0,
        "isAdv": false,
        "cityName": "上海",
        "cityId": 321,
        "productCode": "1000480",
        "productName": "优享窝沟-限上海"
    },
    {
        "id": 87320,
        "externalOfficeCode": "SO8768663726F3332FAA8EA8FB8B6723",
        "name": "瑞伢美口腔连锁.瑞亭口腔",
        "address": "上海市嘉定区安亭镇新源路576号",
        "contactPhone": "4007788190",
        "picUrl": "https://pic5.40017.cn/i/ori/1wueqxlrlEA.png",
        "intro": "",
        "workTime": "9：00-17：00",
        "distanceKm": null,
        "remark": "",
        "customTag": "",
        "qualityGrade": false,
        "demotionRank": 1,
        "invalidProjectConfig": "",
        "verifiedSales": 306,
        "externalId": null,
        "highScoreRatio": 1.0,
        "isAdv": false,
        "cityName": "上海",
        "cityId": 321,
        "productCode": "1000480",
        "productName": "优享窝沟-限上海"
    },
    {
        "id": 87324,
        "externalOfficeCode": "SO424B823C632E36A1ABE795F3B3D010",
        "name": "瑞伢美口腔连锁.瑞而信口腔",
        "address": "上海市长宁区新华路539号（定西路上海银行正对面）",
        "contactPhone": "4007788190",
        "picUrl": "https://pic5.40017.cn/i/ori/1wueqxlrlEA.png",
        "intro": "",
        "workTime": "9：00-17：00",
        "distanceKm": null,
        "remark": "",
        "customTag": "",
        "qualityGrade": false,
        "demotionRank": 1,
        "invalidProjectConfig": "",
        "verifiedSales": 28,
        "externalId": null,
        "highScoreRatio": 0.0,
        "isAdv": false,
        "cityName": "上海",
        "cityId": 321,
        "productCode": "1000480",
        "productName": "优享窝沟-限上海"
    },
    {
        "id": 87319,
        "externalOfficeCode": "SOA51F86D18DE9367A8E0175FC2BBC69",
        "name": "瑞伢美口腔连锁.瑞都口腔",
        "address": "上海市嘉定区嘉定镇城中路200-11号",
        "contactPhone": "4007788190",
        "picUrl": "https://pic5.40017.cn/i/ori/1wueqxlrlEA.png",
        "intro": "",
        "workTime": "9：00-17：00",
        "distanceKm": null,
        "remark": "",
        "customTag": "",
        "qualityGrade": false,
        "demotionRank": 1,
        "invalidProjectConfig": "",
        "verifiedSales": 120,
        "externalId": null,
        "highScoreRatio": 1.0,
        "isAdv": false,
        "cityName": "上海",
        "cityId": 321,
        "productCode": "1000480",
        "productName": "优享窝沟-限上海"
    },
    {
        "id": 87321,
        "externalOfficeCode": "SO9A9B5D581FBF39B580645F81D0E4B8",
        "name": "瑞伢美口腔连锁.瑞雅康口腔",
        "address": "上海市嘉定区裕民路440-444号",
        "contactPhone": "4007788190",
        "picUrl": "https://pic5.40017.cn/i/ori/1wueqxlrlEA.png",
        "intro": "",
        "workTime": "9：00-17：00",
        "distanceKm": null,
        "remark": "",
        "customTag": "",
        "qualityGrade": false,
        "demotionRank": 1,
        "invalidProjectConfig": "",
        "verifiedSales": 32,
        "externalId": null,
        "highScoreRatio": 1.0,
        "isAdv": false,
        "cityName": "上海",
        "cityId": 321,
        "productCode": "1000480",
        "productName": "优享窝沟-限上海"
    },
    {
        "id": 87323,
        "externalOfficeCode": "SO60425B6A4D70341EAABBA2193C88A2",
        "name": "瑞伢美口腔连锁.铭奥口腔",
        "address": "上海市静安区老沪太路266-278号一层",
        "contactPhone": "4007788190",
        "picUrl": "https://pic5.40017.cn/i/ori/1wueqxlrlEA.png",
        "intro": "",
        "workTime": "9：00-17：00",
        "distanceKm": null,
        "remark": "",
        "customTag": "",
        "qualityGrade": false,
        "demotionRank": 1,
        "invalidProjectConfig": "",
        "verifiedSales": 59,
        "externalId": null,
        "highScoreRatio": 1.0,
        "isAdv": false,
        "cityName": "上海",
        "cityId": 321,
        "productCode": "1000480",
        "productName": "优享窝沟-限上海"
    },
    {
        "id": 88642,
        "externalOfficeCode": "SO0604287382633838B98EA29140BEFC",
        "name": "维佳康口腔（嘉尔机构）",
        "address": "青浦区嘉松中路5386弄绿洲智谷花园里北区L3-01\\02-A",
        "contactPhone": "4008203379",
        "picUrl": "https://pic5.40017.cn/i/ori/1zPr31RAWIw.jpg",
        "intro": "",
        "workTime": "9：00-17：00",
        "distanceKm": null,
        "remark": "关爱口腔健康，绽放自信笑容",
        "customTag": "口碑商家",
        "qualityGrade": false,
        "demotionRank": 1,
        "invalidProjectConfig": "",
        "verifiedSales": 230,
        "externalId": null,
        "highScoreRatio": 1.0,
        "isAdv": false,
        "cityName": "上海",
        "cityId": 321,
        "productCode": "1000480",
        "productName": "优享窝沟-限上海"
    },
    {
        "id": 292,
        "externalOfficeCode": "SO64D0A6246038B50267",
        "name": "维佳康口腔（宝山机构）",
        "address": "上海市宝山区经地路99弄经纬汇9号楼2层",
        "contactPhone": "4008203379",
        "picUrl": "https://pic5.40017.cn/i/ori/1wuerQV83i8.png",
        "intro": "",
        "workTime": "9：00-17：00",
        "distanceKm": null,
        "remark": "关爱口腔健康，绽放自信笑容",
        "customTag": "口碑商家",
        "qualityGrade": false,
        "demotionRank": 1,
        "invalidProjectConfig": "",
        "verifiedSales": 607,
        "externalId": null,
        "highScoreRatio": 1.0,
        "isAdv": false,
        "cityName": "上海",
        "cityId": 321,
        "productCode": "1000480",
        "productName": "优享窝沟-限上海"
    },
    {
        "id": 289,
        "externalOfficeCode": "SO64D0A5296038B4U966",
        "name": "维佳康口腔（徐汇机构）",
        "address": "上海市徐汇区龙兰路277号2幢4层01部位2401，2402室",
        "contactPhone": "4008203379",
        "picUrl": "https://pic5.40017.cn/i/ori/1wuerQV83i8.png",
        "intro": "",
        "workTime": "9：00-17：00",
        "distanceKm": null,
        "remark": "关爱口腔健康，绽放自信笑容",
        "customTag": "口碑商家",
        "qualityGrade": false,
        "demotionRank": 1,
        "invalidProjectConfig": "",
        "verifiedSales": 430,
        "externalId": null,
        "highScoreRatio": 1.0,
        "isAdv": false,
        "cityName": "上海",
        "cityId": 321,
        "productCode": "1000480",
        "productName": "优享窝沟-限上海"
    },
    {
        "id": 294,
        "externalOfficeCode": "SO64D0A69F2038B59D11",
        "name": "维佳康口腔（浦尔机构）",
        "address": "上海市青浦区淀浦河东路 229-237 号",
        "contactPhone": "4008203379",
        "picUrl": "https://pic5.40017.cn/i/ori/1wuerQV83i8.png",
        "intro": "",
        "workTime": "9：00-17：00",
        "distanceKm": null,
        "remark": "关爱口腔健康，绽放自信笑容",
        "customTag": "口碑商家",
        "qualityGrade": false,
        "demotionRank": 1,
        "invalidProjectConfig": "",
        "verifiedSales": 105,
        "externalId": null,
        "highScoreRatio": 1.0,
        "isAdv": false,
        "cityName": "上海",
        "cityId": 321,
        "productCode": "1000480",
        "productName": "优享窝沟-限上海"
    },
    {
        "id": 288,
        "externalOfficeCode": "SO64D0A4B26038B4DD9C",
        "name": "维佳康口腔（虹口机构）",
        "address": "上海虹口区公平路 772 号",
        "contactPhone": "4008203379",
        "picUrl": "https://pic5.40017.cn/i/ori/1wuerQV83i8.png",
        "intro": "",
        "workTime": "9：00-17：00",
        "distanceKm": null,
        "remark": "关爱口腔健康，绽放自信笑容",
        "customTag": "口碑商家",
        "qualityGrade": false,
        "demotionRank": 1,
        "invalidProjectConfig": "",
        "verifiedSales": 290,
        "externalId": null,
        "highScoreRatio": 1.0,
        "isAdv": false,
        "cityName": "上海",
        "cityId": 321,
        "productCode": "1000480",
        "productName": "优享窝沟-限上海"
    },
    {
        "id": 291,
        "externalOfficeCode": "SO64D0A5U56038B4FBC5",
        "name": "维佳康口腔（虹桥机构）",
        "address": "上海市青浦区蟠和路588弄中核·和悦荟C4-201",
        "contactPhone": "4008203379",
        "picUrl": "https://pic5.40017.cn/i/ori/1wuerQV83i8.png",
        "intro": "",
        "workTime": "9：00-17：00",
        "distanceKm": null,
        "remark": "关爱口腔健康，绽放自信笑容",
        "customTag": "口碑商家",
        "qualityGrade": false,
        "demotionRank": 1,
        "invalidProjectConfig": "",
        "verifiedSales": 302,
        "externalId": null,
        "highScoreRatio": 1.0,
        "isAdv": false,
        "cityName": "上海",
        "cityId": 321,
        "productCode": "1000480",
        "productName": "优享窝沟-限上海"
    },
    {
        "id": 293,
        "externalOfficeCode": "SO64D0A65C6038B507B4",
        "name": "维佳康口腔（青尔机构）",
        "address": "上海市青浦区盈港路 580 号",
        "contactPhone": "4008203379",
        "picUrl": "https://pic5.40017.cn/i/ori/1wuerQV83i8.png",
        "intro": "",
        "workTime": "9：00-17：00",
        "distanceKm": null,
        "remark": "关爱口腔健康，绽放自信笑容",
        "customTag": "口碑商家",
        "qualityGrade": false,
        "demotionRank": 1,
        "invalidProjectConfig": "",
        "verifiedSales": 141,
        "externalId": null,
        "highScoreRatio": 0.0,
        "isAdv": false,
        "cityName": "上海",
        "cityId": 321,
        "productCode": "1000480",
        "productName": "优享窝沟-限上海"
    },
    {
        "id": 290,
        "externalOfficeCode": "SO64D0A5A36038B4F51C",
        "name": "维佳康口腔（静安机构）",
        "address": "上海市静安区武宁南路395号一层",
        "contactPhone": "4008203379",
        "picUrl": "https://pic5.40017.cn/i/ori/1wuerQV83i8.png",
        "intro": "",
        "workTime": "9：00-17：00",
        "distanceKm": null,
        "remark": "关爱口腔健康，绽放自信笑容",
        "customTag": "口碑商家",
        "qualityGrade": false,
        "demotionRank": 1,
        "invalidProjectConfig": "",
        "verifiedSales": 258,
        "externalId": null,
        "highScoreRatio": 1.0,
        "isAdv": false,
        "cityName": "上海",
        "cityId": 321,
        "productCode": "1000480",
        "productName": "优享窝沟-限上海"
    },
    {
        "id": 94049,
        "externalOfficeCode": "SO15C9A0212BB932F89A37C6ABDF7807",
        "name": "宜兴华齿口腔门诊部",
        "address": "江苏省宜兴市宜城街道荆溪中路174江苏、176号",
        "contactPhone": "051080339599",
        "picUrl": "https://pic5.40017.cn/i/ori/1GYFiJWBTGw.jpg",
        "intro": "",
        "workTime": "9：00-12：00，14：00-18：00",
        "distanceKm": null,
        "remark": "",
        "customTag": "",
        "qualityGrade": false,
        "demotionRank": 0,
        "invalidProjectConfig": "8,4,5",
        "verifiedSales": 3,
        "externalId": null,
        "highScoreRatio": 0.0,
        "isAdv": false,
        "cityName": "无锡",
        "cityId": 229,
        "productCode": "1000480",
        "productName": "优享窝沟-限上海"
    }
]